[
  {
    "timestamp": "2026-06-04T14:29:20.041Z",
    "status": "operational"
  },
  {
    "timestamp": "2026-06-04T14:30:34.608Z",
    "status": "operational"
  },
  {
    "timestamp": "2026-06-04T14:32:47.961Z",
    "status": "outage"
  },
  {
    "timestamp": "2026-06-04T14:33:19.445Z",
    "status": "operational"
  },
  {
    "timestamp": "2026-06-04T14:33:58.582Z",
    "status": "operational"
  },
  {
    "timestamp": "2026-06-04T14:34:20.041Z",
    "status": "operational"
  },
  {
    "timestamp": "2026-06-04T14:35:34.647Z",
    "status": "operational"
  },
  {
    "timestamp": "2026-06-04T14:37:47.961Z",
    "status": "outage"
  },
  {
    "timestamp": "2026-06-04T14:38:19.445Z",
    "status": "operational"
  },
  {
    "timestamp": "2026-06-04T14:38:58.581Z",
    "status": "operational"
  },
  {
    "timestamp": "2026-06-04T14:39:20.042Z",
    "status": "operational"
  },
  {
    "timestamp": "2026-06-04T14:40:34.614Z",
    "status": "operational"
  },
  {
    "timestamp": "2026-06-04T14:42:47.961Z",
    "status": "outage"
  },
  {
    "timestamp": "2026-06-04T14:43:19.445Z",
    "status": "operational"
  },
  {
    "timestamp": "2026-06-04T14:45:34.616Z",
    "status": "operational"
  },
  {
    "timestamp": "2026-06-04T14:45:52.613Z",
    "status": "operational"
  },
  {
    "timestamp": "2026-06-04T14:46:12.244Z",
    "status": "operational"
  },
  {
    "timestamp": "2026-06-04T14:47:47.961Z",
    "status": "outage"
  },
  {
    "timestamp": "2026-06-04T14:48:19.445Z",
    "status": "operational"
  },
  {
    "timestamp": "2026-06-04T14:50:34.656Z",
    "status": "operational"
  },
  {
    "timestamp": "2026-06-04T14:51:36.339Z",
    "status": "operational"
  },
  {
    "timestamp": "2026-06-04T14:52:08.022Z",
    "status": "operational"
  },
  {
    "timestamp": "2026-06-04T14:52:47.961Z",
    "status": "outage"
  },
  {
    "timestamp": "2026-06-04T14:53:19.446Z",
    "status": "operational"
  },
  {
    "timestamp": "2026-06-04T14:55:34.618Z",
    "status": "operational"
  },
  {
    "timestamp": "2026-06-04T14:56:36.333Z",
    "status": "operational"
  },
  {
    "timestamp": "2026-06-04T14:57:47.962Z",
    "status": "outage"
  },
  {
    "timestamp": "2026-06-04T14:58:19.447Z",
    "status": "operational"
  },
  {
    "timestamp": "2026-06-04T15:00:34.619Z",
    "status": "operational"
  },
  {
    "timestamp": "2026-06-04T15:02:47.961Z",
    "status": "outage"
  },
  {
    "timestamp": "2026-06-04T15:03:19.446Z",
    "status": "operational"
  },
  {
    "timestamp": "2026-06-04T15:05:34.621Z",
    "status": "operational"
  },
  {
    "timestamp": "2026-06-04T15:06:09.894Z",
    "status": "operational"
  },
  {
    "timestamp": "2026-06-04T15:06:18.528Z",
    "status": "operational"
  },
  {
    "timestamp": "2026-06-04T15:07:47.961Z",
    "status": "outage"
  },
  {
    "timestamp": "2026-06-04T15:08:19.446Z",
    "status": "operational"
  },
  {
    "timestamp": "2026-06-04T15:10:34.622Z",
    "status": "operational"
  },
  {
    "timestamp": "2026-06-04T15:11:09.878Z",
    "status": "operational"
  },
  {
    "timestamp": "2026-06-04T15:11:18.524Z",
    "status": "operational"
  },
  {
    "timestamp": "2026-06-04T15:12:47.961Z",
    "status": "outage"
  },
  {
    "timestamp": "2026-06-04T15:13:19.447Z",
    "status": "operational"
  },
  {
    "timestamp": "2026-06-04T15:15:34.623Z",
    "status": "operational"
  },
  {
    "timestamp": "2026-06-04T15:16:25.036Z",
    "status": "operational"
  },
  {
    "timestamp": "2026-06-04T15:16:47.253Z",
    "status": "operational"
  },
  {
    "timestamp": "2026-06-04T15:17:47.962Z",
    "status": "outage"
  },
  {
    "timestamp": "2026-06-04T15:18:19.447Z",
    "status": "operational"
  },
  {
    "timestamp": "2026-06-04T15:20:34.625Z",
    "status": "operational"
  },
  {
    "timestamp": "2026-06-04T15:21:25.025Z",
    "status": "operational"
  },
  {
    "timestamp": "2026-06-04T15:21:47.233Z",
    "status": "operational"
  },
  {
    "timestamp": "2026-06-04T15:22:47.961Z",
    "status": "outage"
  },
  {
    "timestamp": "2026-06-04T15:25:34.627Z",
    "status": "operational"
  },
  {
    "timestamp": "2026-06-04T15:26:25.018Z",
    "status": "operational"
  },
  {
    "timestamp": "2026-06-04T15:26:45.738Z",
    "status": "operational"
  },
  {
    "timestamp": "2026-06-04T15:26:47.231Z",
    "status": "operational"
  },
  {
    "timestamp": "2026-06-04T15:27:47.961Z",
    "status": "outage"
  },
  {
    "timestamp": "2026-06-04T15:30:34.626Z",
    "status": "operational"
  },
  {
    "timestamp": "2026-06-04T15:31:25.018Z",
    "status": "operational"
  },
  {
    "timestamp": "2026-06-04T15:31:45.730Z",
    "status": "operational"
  },
  {
    "timestamp": "2026-06-04T15:31:47.224Z",
    "status": "operational"
  },
  {
    "timestamp": "2026-06-04T15:32:47.961Z",
    "status": "outage"
  },
  {
    "timestamp": "2026-06-04T15:35:34.629Z",
    "status": "operational"
  },
  {
    "timestamp": "2026-06-04T15:36:18.929Z",
    "status": "operational"
  },
  {
    "timestamp": "2026-06-04T15:36:25.017Z",
    "status": "operational"
  },
  {
    "timestamp": "2026-06-04T15:36:45.731Z",
    "status": "operational"
  },
  {
    "timestamp": "2026-06-04T15:36:47.223Z",
    "status": "operational"
  },
  {
    "timestamp": "2026-06-04T15:37:47.962Z",
    "status": "outage"
  },
  {
    "timestamp": "2026-06-04T15:40:34.630Z",
    "status": "operational"
  },
  {
    "timestamp": "2026-06-04T15:41:18.919Z",
    "status": "operational"
  },
  {
    "timestamp": "2026-06-04T15:41:25.024Z",
    "status": "operational"
  },
  {
    "timestamp": "2026-06-04T15:41:45.733Z",
    "status": "operational"
  },
  {
    "timestamp": "2026-06-04T15:41:47.225Z",
    "status": "operational"
  },
  {
    "timestamp": "2026-06-04T15:42:47.963Z",
    "status": "outage"
  },
  {
    "timestamp": "2026-06-04T15:45:34.630Z",
    "status": "operational"
  },
  {
    "timestamp": "2026-06-04T15:46:18.915Z",
    "status": "operational"
  },
  {
    "timestamp": "2026-06-04T15:46:45.733Z",
    "status": "operational"
  },
  {
    "timestamp": "2026-06-04T15:47:47.962Z",
    "status": "outage"
  },
  {
    "timestamp": "2026-06-04T15:48:47.846Z",
    "status": "operational"
  },
  {
    "timestamp": "2026-06-04T15:50:34.630Z",
    "status": "operational"
  },
  {
    "timestamp": "2026-06-04T15:50:54.724Z",
    "status": "operational"
  },
  {
    "timestamp": "2026-06-04T15:51:18.915Z",
    "status": "operational"
  },
  {
    "timestamp": "2026-06-04T15:51:45.732Z",
    "status": "operational"
  },
  {
    "timestamp": "2026-06-04T15:52:47.961Z",
    "status": "outage"
  },
  {
    "timestamp": "2026-06-04T15:53:47.835Z",
    "status": "operational"
  },
  {
    "timestamp": "2026-06-04T15:55:34.631Z",
    "status": "operational"
  },
  {
    "timestamp": "2026-06-04T15:55:54.716Z",
    "status": "operational"
  },
  {
    "timestamp": "2026-06-04T15:56:18.916Z",
    "status": "operational"
  },
  {
    "timestamp": "2026-06-04T15:56:45.734Z",
    "status": "operational"
  },
  {
    "timestamp": "2026-06-04T15:57:47.963Z",
    "status": "outage"
  },
  {
    "timestamp": "2026-06-04T15:58:47.831Z",
    "status": "operational"
  },
  {
    "timestamp": "2026-06-04T16:00:34.631Z",
    "status": "operational"
  },
  {
    "timestamp": "2026-06-04T16:00:54.713Z",
    "status": "operational"
  },
  {
    "timestamp": "2026-06-04T16:01:18.920Z",
    "status": "operational"
  },
  {
    "timestamp": "2026-06-04T16:01:45.746Z",
    "status": "operational"
  },
  {
    "timestamp": "2026-06-04T16:02:47.961Z",
    "status": "outage"
  },
  {
    "timestamp": "2026-06-04T16:03:47.830Z",
    "status": "operational"
  },
  {
    "timestamp": "2026-06-04T16:05:34.632Z",
    "status": "operational"
  },
  {
    "timestamp": "2026-06-04T16:05:54.712Z",
    "status": "operational"
  },
  {
    "timestamp": "2026-06-04T16:06:18.920Z",
    "status": "operational"
  },
  {
    "timestamp": "2026-06-04T16:06:45.740Z",
    "status": "operational"
  },
  {
    "timestamp": "2026-06-04T16:07:47.963Z",
    "status": "outage"
  },
  {
    "timestamp": "2026-06-04T16:08:47.830Z",
    "status": "operational"
  },
  {
    "timestamp": "2026-06-04T16:10:34.635Z",
    "status": "operational"
  },
  {
    "timestamp": "2026-06-04T16:10:54.713Z",
    "status": "operational"
  },
  {
    "timestamp": "2026-06-04T16:11:18.921Z",
    "status": "operational"
  },
  {
    "timestamp": "2026-06-04T16:11:45.739Z",
    "status": "operational"
  },
  {
    "timestamp": "2026-06-04T16:12:48.015Z",
    "status": "outage"
  },
  {
    "timestamp": "2026-06-04T16:13:47.835Z",
    "status": "operational"
  },
  {
    "timestamp": "2026-06-04T16:15:34.638Z",
    "status": "operational"
  },
  {
    "timestamp": "2026-06-04T16:15:54.715Z",
    "status": "operational"
  },
  {
    "timestamp": "2026-06-04T16:16:18.922Z",
    "status": "operational"
  },
  {
    "timestamp": "2026-06-04T16:16:45.741Z",
    "status": "operational"
  },
  {
    "timestamp": "2026-06-04T16:17:47.963Z",
    "status": "outage"
  },
  {
    "timestamp": "2026-06-04T16:18:47.836Z",
    "status": "operational"
  },
  {
    "timestamp": "2026-06-04T16:20:34.639Z",
    "status": "operational"
  },
  {
    "timestamp": "2026-06-04T16:20:54.716Z",
    "status": "operational"
  },
  {
    "timestamp": "2026-06-04T16:21:18.922Z",
    "status": "operational"
  },
  {
    "timestamp": "2026-06-04T16:21:45.743Z",
    "status": "operational"
  },
  {
    "timestamp": "2026-06-04T16:22:47.962Z",
    "status": "outage"
  },
  {
    "timestamp": "2026-06-04T16:23:47.836Z",
    "status": "operational"
  },
  {
    "timestamp": "2026-06-04T16:25:34.642Z",
    "status": "operational"
  },
  {
    "timestamp": "2026-06-04T16:25:54.717Z",
    "status": "operational"
  },
  {
    "timestamp": "2026-06-04T16:26:18.922Z",
    "status": "operational"
  },
  {
    "timestamp": "2026-06-04T16:26:45.742Z",
    "status": "operational"
  },
  {
    "timestamp": "2026-06-04T16:27:47.962Z",
    "status": "outage"
  },
  {
    "timestamp": "2026-06-04T16:30:34.646Z",
    "status": "operational"
  },
  {
    "timestamp": "2026-06-04T16:31:18.921Z",
    "status": "operational"
  },
  {
    "timestamp": "2026-06-04T16:31:45.742Z",
    "status": "operational"
  },
  {
    "timestamp": "2026-06-04T16:32:46.355Z",
    "status": "operational"
  },
  {
    "timestamp": "2026-06-04T16:32:47.964Z",
    "status": "outage"
  },
  {
    "timestamp": "2026-06-04T16:32:54.785Z",
    "status": "operational"
  },
  {
    "timestamp": "2026-06-04T16:35:34.649Z",
    "status": "operational"
  },
  {
    "timestamp": "2026-06-04T16:37:17.009Z",
    "status": "operational"
  },
  {
    "timestamp": "2026-06-04T16:37:32.953Z",
    "status": "operational"
  },
  {
    "timestamp": "2026-06-04T16:37:46.330Z",
    "status": "operational"
  },
  {
    "timestamp": "2026-06-04T16:37:47.967Z",
    "status": "outage"
  },
  {
    "timestamp": "2026-06-04T16:37:54.779Z",
    "status": "operational"
  },
  {
    "timestamp": "2026-06-04T16:40:34.653Z",
    "status": "operational"
  },
  {
    "timestamp": "2026-06-04T16:42:16.993Z",
    "status": "operational"
  },
  {
    "timestamp": "2026-06-04T16:42:32.946Z",
    "status": "operational"
  },
  {
    "timestamp": "2026-06-04T16:42:46.325Z",
    "status": "operational"
  },
  {
    "timestamp": "2026-06-04T16:42:47.968Z",
    "status": "outage"
  },
  {
    "timestamp": "2026-06-04T16:42:54.776Z",
    "status": "operational"
  },
  {
    "timestamp": "2026-06-04T16:45:34.654Z",
    "status": "operational"
  },
  {
    "timestamp": "2026-06-04T16:47:16.988Z",
    "status": "operational"
  },
  {
    "timestamp": "2026-06-04T16:47:32.945Z",
    "status": "operational"
  },
  {
    "timestamp": "2026-06-04T16:47:46.327Z",
    "status": "operational"
  },
  {
    "timestamp": "2026-06-04T16:47:54.777Z",
    "status": "operational"
  },
  {
    "timestamp": "2026-06-04T16:50:34.657Z",
    "status": "operational"
  },
  {
    "timestamp": "2026-06-04T16:52:17.002Z",
    "status": "operational"
  },
  {
    "timestamp": "2026-06-04T16:52:32.947Z",
    "status": "operational"
  },
  {
    "timestamp": "2026-06-04T16:52:46.327Z",
    "status": "operational"
  },
  {
    "timestamp": "2026-06-04T16:52:47.970Z",
    "status": "outage"
  },
  {
    "timestamp": "2026-06-04T16:52:54.777Z",
    "status": "outage"
  },
  {
    "timestamp": "2026-06-04T16:55:34.658Z",
    "status": "operational"
  },
  {
    "timestamp": "2026-06-04T16:57:16.989Z",
    "status": "operational"
  },
  {
    "timestamp": "2026-06-04T16:57:32.946Z",
    "status": "operational"
  },
  {
    "timestamp": "2026-06-04T16:57:46.329Z",
    "status": "operational"
  },
  {
    "timestamp": "2026-06-04T16:57:47.975Z",
    "status": "outage"
  },
  {
    "timestamp": "2026-06-04T16:57:54.779Z",
    "status": "operational"
  },
  {
    "timestamp": "2026-06-04T17:00:34.660Z",
    "status": "operational"
  },
  {
    "timestamp": "2026-06-04T17:02:16.996Z",
    "status": "operational"
  },
  {
    "timestamp": "2026-06-04T17:02:32.948Z",
    "status": "operational"
  },
  {
    "timestamp": "2026-06-04T17:02:46.330Z",
    "status": "operational"
  },
  {
    "timestamp": "2026-06-04T17:02:48.038Z",
    "status": "outage"
  },
  {
    "timestamp": "2026-06-04T17:02:54.778Z",
    "status": "operational"
  },
  {
    "timestamp": "2026-06-04T17:05:34.665Z",
    "status": "operational"
  },
  {
    "timestamp": "2026-06-04T17:07:16.994Z",
    "status": "operational"
  },
  {
    "timestamp": "2026-06-04T17:07:32.950Z",
    "status": "operational"
  },
  {
    "timestamp": "2026-06-04T17:07:46.331Z",
    "status": "operational"
  },
  {
    "timestamp": "2026-06-04T17:07:47.978Z",
    "status": "outage"
  },
  {
    "timestamp": "2026-06-04T17:07:54.778Z",
    "status": "operational"
  },
  {
    "timestamp": "2026-06-04T17:10:34.665Z",
    "status": "operational"
  },
  {
    "timestamp": "2026-06-04T17:12:16.995Z",
    "status": "operational"
  },
  {
    "timestamp": "2026-06-04T17:12:32.950Z",
    "status": "operational"
  },
  {
    "timestamp": "2026-06-04T17:12:46.332Z",
    "status": "operational"
  },
  {
    "timestamp": "2026-06-04T17:12:47.975Z",
    "status": "outage"
  },
  {
    "timestamp": "2026-06-04T17:15:34.666Z",
    "status": "operational"
  },
  {
    "timestamp": "2026-06-04T17:17:37.842Z",
    "status": "operational"
  },
  {
    "timestamp": "2026-06-04T17:17:46.153Z",
    "status": "operational"
  },
  {
    "timestamp": "2026-06-04T17:17:47.975Z",
    "status": "outage"
  },
  {
    "timestamp": "2026-06-04T17:18:24.892Z",
    "status": "operational"
  },
  {
    "timestamp": "2026-06-04T17:18:40.041Z",
    "status": "operational"
  },
  {
    "timestamp": "2026-06-04T17:20:34.668Z",
    "status": "operational"
  },
  {
    "timestamp": "2026-06-04T17:22:37.831Z",
    "status": "operational"
  },
  {
    "timestamp": "2026-06-04T17:22:46.153Z",
    "status": "operational"
  },
  {
    "timestamp": "2026-06-04T17:22:47.978Z",
    "status": "outage"
  },
  {
    "timestamp": "2026-06-04T17:23:24.888Z",
    "status": "operational"
  },
  {
    "timestamp": "2026-06-04T17:23:40.029Z",
    "status": "operational"
  },
  {
    "timestamp": "2026-06-04T17:25:34.670Z",
    "status": "operational"
  },
  {
    "timestamp": "2026-06-04T17:27:37.828Z",
    "status": "operational"
  },
  {
    "timestamp": "2026-06-04T17:27:46.153Z",
    "status": "operational"
  },
  {
    "timestamp": "2026-06-04T17:27:47.979Z",
    "status": "outage"
  },
  {
    "timestamp": "2026-06-04T17:28:24.883Z",
    "status": "operational"
  },
  {
    "timestamp": "2026-06-04T17:28:40.026Z",
    "status": "operational"
  },
  {
    "timestamp": "2026-06-04T17:30:34.673Z",
    "status": "operational"
  },
  {
    "timestamp": "2026-06-04T17:32:37.828Z",
    "status": "operational"
  },
  {
    "timestamp": "2026-06-04T17:32:46.154Z",
    "status": "operational"
  },
  {
    "timestamp": "2026-06-04T17:32:47.979Z",
    "status": "outage"
  },
  {
    "timestamp": "2026-06-04T17:33:24.885Z",
    "status": "operational"
  },
  {
    "timestamp": "2026-06-04T17:33:40.025Z",
    "status": "operational"
  },
  {
    "timestamp": "2026-06-04T17:35:34.674Z",
    "status": "operational"
  },
  {
    "timestamp": "2026-06-04T17:37:37.829Z",
    "status": "operational"
  },
  {
    "timestamp": "2026-06-04T17:37:46.155Z",
    "status": "operational"
  },
  {
    "timestamp": "2026-06-04T17:37:47.983Z",
    "status": "outage"
  },
  {
    "timestamp": "2026-06-04T17:38:24.884Z",
    "status": "operational"
  },
  {
    "timestamp": "2026-06-04T17:38:40.025Z",
    "status": "operational"
  },
  {
    "timestamp": "2026-06-04T17:40:34.676Z",
    "status": "operational"
  },
  {
    "timestamp": "2026-06-04T17:42:37.831Z",
    "status": "operational"
  },
  {
    "timestamp": "2026-06-04T17:42:46.157Z",
    "status": "operational"
  },
  {
    "timestamp": "2026-06-04T17:42:47.984Z",
    "status": "outage"
  },
  {
    "timestamp": "2026-06-04T17:43:24.887Z",
    "status": "operational"
  },
  {
    "timestamp": "2026-06-04T17:43:40.032Z",
    "status": "operational"
  },
  {
    "timestamp": "2026-06-04T17:45:34.677Z",
    "status": "operational"
  },
  {
    "timestamp": "2026-06-04T17:47:37.832Z",
    "status": "operational"
  },
  {
    "timestamp": "2026-06-04T17:47:46.154Z",
    "status": "operational"
  },
  {
    "timestamp": "2026-06-04T17:47:47.985Z",
    "status": "outage"
  },
  {
    "timestamp": "2026-06-04T17:48:24.889Z",
    "status": "operational"
  },
  {
    "timestamp": "2026-06-04T17:48:40.032Z",
    "status": "operational"
  },
  {
    "timestamp": "2026-06-04T17:50:34.678Z",
    "status": "operational"
  },
  {
    "timestamp": "2026-06-04T17:52:37.832Z",
    "status": "operational"
  },
  {
    "timestamp": "2026-06-04T17:52:46.155Z",
    "status": "operational"
  },
  {
    "timestamp": "2026-06-04T17:52:47.987Z",
    "status": "outage"
  },
  {
    "timestamp": "2026-06-04T17:53:24.890Z",
    "status": "operational"
  },
  {
    "timestamp": "2026-06-04T17:53:40.035Z",
    "status": "operational"
  },
  {
    "timestamp": "2026-06-04T17:55:34.678Z",
    "status": "operational"
  },
  {
    "timestamp": "2026-06-04T17:57:37.832Z",
    "status": "operational"
  },
  {
    "timestamp": "2026-06-04T17:57:46.155Z",
    "status": "operational"
  },
  {
    "timestamp": "2026-06-04T17:57:47.989Z",
    "status": "outage"
  },
  {
    "timestamp": "2026-06-04T17:58:24.892Z",
    "status": "operational"
  },
  {
    "timestamp": "2026-06-04T17:58:40.034Z",
    "status": "operational"
  },
  {
    "timestamp": "2026-06-04T18:00:34.679Z",
    "status": "operational"
  },
  {
    "timestamp": "2026-06-04T18:02:37.832Z",
    "status": "operational"
  },
  {
    "timestamp": "2026-06-04T18:02:46.155Z",
    "status": "operational"
  },
  {
    "timestamp": "2026-06-04T18:02:47.993Z",
    "status": "outage"
  },
  {
    "timestamp": "2026-06-04T18:03:24.891Z",
    "status": "operational"
  },
  {
    "timestamp": "2026-06-04T18:03:40.034Z",
    "status": "operational"
  },
  {
    "timestamp": "2026-06-04T18:05:34.678Z",
    "status": "operational"
  },
  {
    "timestamp": "2026-06-04T18:07:37.833Z",
    "status": "operational"
  },
  {
    "timestamp": "2026-06-04T18:07:46.155Z",
    "status": "operational"
  },
  {
    "timestamp": "2026-06-04T18:07:47.998Z",
    "status": "outage"
  },
  {
    "timestamp": "2026-06-04T18:08:24.891Z",
    "status": "operational"
  },
  {
    "timestamp": "2026-06-04T18:08:40.036Z",
    "status": "operational"
  },
  {
    "timestamp": "2026-06-04T18:10:34.679Z",
    "status": "operational"
  },
  {
    "timestamp": "2026-06-04T18:12:37.835Z",
    "status": "operational"
  },
  {
    "timestamp": "2026-06-04T18:12:46.155Z",
    "status": "operational"
  },
  {
    "timestamp": "2026-06-04T18:12:48.001Z",
    "status": "outage"
  },
  {
    "timestamp": "2026-06-04T18:13:24.893Z",
    "status": "operational"
  },
  {
    "timestamp": "2026-06-04T18:13:40.034Z",
    "status": "operational"
  },
  {
    "timestamp": "2026-06-04T18:15:34.680Z",
    "status": "operational"
  },
  {
    "timestamp": "2026-06-04T18:17:37.835Z",
    "status": "operational"
  },
  {
    "timestamp": "2026-06-04T18:17:46.154Z",
    "status": "operational"
  },
  {
    "timestamp": "2026-06-04T18:17:48.000Z",
    "status": "outage"
  },
  {
    "timestamp": "2026-06-04T18:18:24.892Z",
    "status": "operational"
  },
  {
    "timestamp": "2026-06-04T18:18:40.035Z",
    "status": "operational"
  },
  {
    "timestamp": "2026-06-04T18:20:34.681Z",
    "status": "operational"
  },
  {
    "timestamp": "2026-06-04T18:22:37.834Z",
    "status": "operational"
  },
  {
    "timestamp": "2026-06-04T18:22:46.155Z",
    "status": "operational"
  },
  {
    "timestamp": "2026-06-04T18:22:48.006Z",
    "status": "outage"
  },
  {
    "timestamp": "2026-06-04T18:23:24.891Z",
    "status": "operational"
  },
  {
    "timestamp": "2026-06-04T18:23:40.036Z",
    "status": "operational"
  },
  {
    "timestamp": "2026-06-04T18:25:34.686Z",
    "status": "operational"
  },
  {
    "timestamp": "2026-06-04T18:27:37.835Z",
    "status": "operational"
  },
  {
    "timestamp": "2026-06-04T18:27:46.156Z",
    "status": "operational"
  },
  {
    "timestamp": "2026-06-04T18:27:48.008Z",
    "status": "outage"
  },
  {
    "timestamp": "2026-06-04T18:28:24.892Z",
    "status": "operational"
  },
  {
    "timestamp": "2026-06-04T18:28:40.037Z",
    "status": "operational"
  },
  {
    "timestamp": "2026-06-04T18:30:34.691Z",
    "status": "operational"
  },
  {
    "timestamp": "2026-06-04T18:32:37.833Z",
    "status": "operational"
  },
  {
    "timestamp": "2026-06-04T18:32:46.156Z",
    "status": "operational"
  },
  {
    "timestamp": "2026-06-04T18:32:48.009Z",
    "status": "outage"
  },
  {
    "timestamp": "2026-06-04T18:33:24.891Z",
    "status": "operational"
  },
  {
    "timestamp": "2026-06-04T18:33:40.036Z",
    "status": "operational"
  },
  {
    "timestamp": "2026-06-04T18:35:34.697Z",
    "status": "operational"
  },
  {
    "timestamp": "2026-06-04T18:37:37.834Z",
    "status": "operational"
  },
  {
    "timestamp": "2026-06-04T18:37:46.155Z",
    "status": "operational"
  },
  {
    "timestamp": "2026-06-04T18:37:48.012Z",
    "status": "outage"
  },
  {
    "timestamp": "2026-06-04T18:38:24.892Z",
    "status": "operational"
  },
  {
    "timestamp": "2026-06-04T18:38:40.038Z",
    "status": "operational"
  },
  {
    "timestamp": "2026-06-04T18:40:34.697Z",
    "status": "operational"
  },
  {
    "timestamp": "2026-06-04T18:42:37.833Z",
    "status": "operational"
  },
  {
    "timestamp": "2026-06-04T18:42:46.157Z",
    "status": "operational"
  },
  {
    "timestamp": "2026-06-04T18:42:48.011Z",
    "status": "outage"
  },
  {
    "timestamp": "2026-06-04T18:43:24.892Z",
    "status": "operational"
  },
  {
    "timestamp": "2026-06-04T18:43:40.039Z",
    "status": "operational"
  },
  {
    "timestamp": "2026-06-04T18:45:34.699Z",
    "status": "operational"
  },
  {
    "timestamp": "2026-06-04T18:47:37.833Z",
    "status": "operational"
  },
  {
    "timestamp": "2026-06-04T18:47:46.156Z",
    "status": "operational"
  },
  {
    "timestamp": "2026-06-04T18:47:48.010Z",
    "status": "outage"
  }
]