[
  {
    "timestamp": "2026-06-18T20:41:36.438Z",
    "status": "operational"
  },
  {
    "timestamp": "2026-06-18T20:44:33.529Z",
    "status": "operational"
  },
  {
    "timestamp": "2026-06-18T20:45:42.574Z",
    "status": "operational"
  },
  {
    "timestamp": "2026-06-18T20:46:36.440Z",
    "status": "operational"
  },
  {
    "timestamp": "2026-06-18T20:49:33.529Z",
    "status": "operational"
  },
  {
    "timestamp": "2026-06-18T20:50:42.575Z",
    "status": "operational"
  },
  {
    "timestamp": "2026-06-18T20:51:36.439Z",
    "status": "operational"
  },
  {
    "timestamp": "2026-06-18T20:54:33.529Z",
    "status": "operational"
  },
  {
    "timestamp": "2026-06-18T20:55:42.574Z",
    "status": "operational"
  },
  {
    "timestamp": "2026-06-18T20:56:36.439Z",
    "status": "operational"
  },
  {
    "timestamp": "2026-06-18T20:59:33.528Z",
    "status": "operational"
  },
  {
    "timestamp": "2026-06-18T21:00:42.575Z",
    "status": "operational"
  },
  {
    "timestamp": "2026-06-18T21:01:36.439Z",
    "status": "operational"
  },
  {
    "timestamp": "2026-06-18T21:04:33.529Z",
    "status": "operational"
  },
  {
    "timestamp": "2026-06-18T21:05:42.613Z",
    "status": "operational"
  },
  {
    "timestamp": "2026-06-18T21:06:36.496Z",
    "status": "operational"
  },
  {
    "timestamp": "2026-06-18T21:09:33.530Z",
    "status": "operational"
  },
  {
    "timestamp": "2026-06-18T21:10:42.575Z",
    "status": "operational"
  },
  {
    "timestamp": "2026-06-18T21:11:36.439Z",
    "status": "operational"
  },
  {
    "timestamp": "2026-06-18T21:14:33.531Z",
    "status": "operational"
  },
  {
    "timestamp": "2026-06-18T21:15:42.574Z",
    "status": "operational"
  },
  {
    "timestamp": "2026-06-18T21:16:36.440Z",
    "status": "operational"
  },
  {
    "timestamp": "2026-06-18T21:19:33.532Z",
    "status": "operational"
  },
  {
    "timestamp": "2026-06-18T21:20:42.575Z",
    "status": "operational"
  },
  {
    "timestamp": "2026-06-18T21:21:36.439Z",
    "status": "operational"
  },
  {
    "timestamp": "2026-06-18T21:24:33.532Z",
    "status": "operational"
  },
  {
    "timestamp": "2026-06-18T21:25:42.628Z",
    "status": "operational"
  },
  {
    "timestamp": "2026-06-18T21:26:36.439Z",
    "status": "operational"
  },
  {
    "timestamp": "2026-06-18T21:29:33.531Z",
    "status": "operational"
  },
  {
    "timestamp": "2026-06-18T21:30:42.576Z",
    "status": "operational"
  },
  {
    "timestamp": "2026-06-18T21:31:36.439Z",
    "status": "operational"
  },
  {
    "timestamp": "2026-06-18T21:34:33.532Z",
    "status": "operational"
  },
  {
    "timestamp": "2026-06-18T21:35:42.574Z",
    "status": "operational"
  },
  {
    "timestamp": "2026-06-18T21:36:36.439Z",
    "status": "operational"
  },
  {
    "timestamp": "2026-06-18T21:39:33.572Z",
    "status": "operational"
  },
  {
    "timestamp": "2026-06-18T21:40:42.575Z",
    "status": "operational"
  },
  {
    "timestamp": "2026-06-18T21:41:36.440Z",
    "status": "operational"
  },
  {
    "timestamp": "2026-06-18T21:44:33.532Z",
    "status": "operational"
  },
  {
    "timestamp": "2026-06-18T21:45:42.574Z",
    "status": "operational"
  },
  {
    "timestamp": "2026-06-18T21:46:36.441Z",
    "status": "operational"
  },
  {
    "timestamp": "2026-06-18T21:49:33.531Z",
    "status": "operational"
  },
  {
    "timestamp": "2026-06-18T21:50:42.576Z",
    "status": "operational"
  },
  {
    "timestamp": "2026-06-18T21:51:36.442Z",
    "status": "operational"
  },
  {
    "timestamp": "2026-06-18T21:54:33.532Z",
    "status": "operational"
  },
  {
    "timestamp": "2026-06-18T21:55:42.574Z",
    "status": "operational"
  },
  {
    "timestamp": "2026-06-18T21:56:36.443Z",
    "status": "operational"
  },
  {
    "timestamp": "2026-06-18T21:59:33.532Z",
    "status": "operational"
  },
  {
    "timestamp": "2026-06-18T22:00:42.621Z",
    "status": "operational"
  },
  {
    "timestamp": "2026-06-18T22:01:36.442Z",
    "status": "operational"
  },
  {
    "timestamp": "2026-06-18T22:04:33.531Z",
    "status": "operational"
  },
  {
    "timestamp": "2026-06-18T22:05:42.575Z",
    "status": "operational"
  },
  {
    "timestamp": "2026-06-18T22:06:36.443Z",
    "status": "operational"
  },
  {
    "timestamp": "2026-06-18T22:09:33.532Z",
    "status": "operational"
  },
  {
    "timestamp": "2026-06-18T22:10:42.575Z",
    "status": "operational"
  },
  {
    "timestamp": "2026-06-18T22:11:36.443Z",
    "status": "operational"
  },
  {
    "timestamp": "2026-06-18T22:14:33.532Z",
    "status": "operational"
  },
  {
    "timestamp": "2026-06-18T22:15:42.652Z",
    "status": "operational"
  },
  {
    "timestamp": "2026-06-18T22:16:36.443Z",
    "status": "operational"
  },
  {
    "timestamp": "2026-06-18T22:19:33.532Z",
    "status": "operational"
  },
  {
    "timestamp": "2026-06-18T22:20:42.576Z",
    "status": "operational"
  },
  {
    "timestamp": "2026-06-18T22:21:36.444Z",
    "status": "operational"
  },
  {
    "timestamp": "2026-06-18T22:24:33.532Z",
    "status": "operational"
  },
  {
    "timestamp": "2026-06-18T22:25:42.577Z",
    "status": "operational"
  },
  {
    "timestamp": "2026-06-18T22:26:36.457Z",
    "status": "operational"
  },
  {
    "timestamp": "2026-06-18T22:29:33.533Z",
    "status": "operational"
  },
  {
    "timestamp": "2026-06-18T22:30:42.576Z",
    "status": "operational"
  },
  {
    "timestamp": "2026-06-18T22:31:36.444Z",
    "status": "operational"
  },
  {
    "timestamp": "2026-06-18T22:34:33.532Z",
    "status": "operational"
  },
  {
    "timestamp": "2026-06-18T22:35:42.576Z",
    "status": "operational"
  },
  {
    "timestamp": "2026-06-18T22:36:36.443Z",
    "status": "operational"
  },
  {
    "timestamp": "2026-06-18T22:39:33.532Z",
    "status": "operational"
  },
  {
    "timestamp": "2026-06-18T22:40:42.577Z",
    "status": "operational"
  },
  {
    "timestamp": "2026-06-18T22:41:36.443Z",
    "status": "operational"
  },
  {
    "timestamp": "2026-06-18T22:44:33.533Z",
    "status": "operational"
  },
  {
    "timestamp": "2026-06-18T22:45:42.576Z",
    "status": "operational"
  },
  {
    "timestamp": "2026-06-18T22:46:36.445Z",
    "status": "operational"
  },
  {
    "timestamp": "2026-06-18T22:49:33.533Z",
    "status": "operational"
  },
  {
    "timestamp": "2026-06-18T22:50:42.576Z",
    "status": "operational"
  },
  {
    "timestamp": "2026-06-18T22:51:36.444Z",
    "status": "operational"
  },
  {
    "timestamp": "2026-06-18T22:54:33.534Z",
    "status": "operational"
  },
  {
    "timestamp": "2026-06-18T22:55:42.576Z",
    "status": "operational"
  },
  {
    "timestamp": "2026-06-18T22:56:36.443Z",
    "status": "operational"
  },
  {
    "timestamp": "2026-06-18T22:59:33.533Z",
    "status": "operational"
  },
  {
    "timestamp": "2026-06-18T23:00:42.577Z",
    "status": "operational"
  },
  {
    "timestamp": "2026-06-18T23:01:36.443Z",
    "status": "operational"
  },
  {
    "timestamp": "2026-06-18T23:04:33.534Z",
    "status": "operational"
  },
  {
    "timestamp": "2026-06-18T23:05:42.576Z",
    "status": "operational"
  },
  {
    "timestamp": "2026-06-18T23:06:36.444Z",
    "status": "operational"
  },
  {
    "timestamp": "2026-06-18T23:09:33.534Z",
    "status": "operational"
  },
  {
    "timestamp": "2026-06-18T23:10:42.576Z",
    "status": "operational"
  },
  {
    "timestamp": "2026-06-18T23:11:36.445Z",
    "status": "operational"
  },
  {
    "timestamp": "2026-06-18T23:14:33.535Z",
    "status": "operational"
  },
  {
    "timestamp": "2026-06-18T23:15:42.660Z",
    "status": "operational"
  },
  {
    "timestamp": "2026-06-18T23:16:36.444Z",
    "status": "operational"
  },
  {
    "timestamp": "2026-06-18T23:19:33.534Z",
    "status": "operational"
  },
  {
    "timestamp": "2026-06-18T23:20:42.578Z",
    "status": "operational"
  },
  {
    "timestamp": "2026-06-18T23:21:36.444Z",
    "status": "operational"
  },
  {
    "timestamp": "2026-06-18T23:24:33.533Z",
    "status": "operational"
  },
  {
    "timestamp": "2026-06-18T23:25:42.586Z",
    "status": "operational"
  },
  {
    "timestamp": "2026-06-18T23:26:36.448Z",
    "status": "operational"
  },
  {
    "timestamp": "2026-06-18T23:29:33.534Z",
    "status": "operational"
  },
  {
    "timestamp": "2026-06-18T23:30:42.577Z",
    "status": "operational"
  },
  {
    "timestamp": "2026-06-18T23:31:36.444Z",
    "status": "operational"
  },
  {
    "timestamp": "2026-06-18T23:34:33.533Z",
    "status": "operational"
  },
  {
    "timestamp": "2026-06-18T23:35:42.576Z",
    "status": "operational"
  },
  {
    "timestamp": "2026-06-18T23:36:36.446Z",
    "status": "operational"
  },
  {
    "timestamp": "2026-06-18T23:39:33.534Z",
    "status": "operational"
  },
  {
    "timestamp": "2026-06-18T23:40:42.576Z",
    "status": "operational"
  },
  {
    "timestamp": "2026-06-18T23:41:36.446Z",
    "status": "operational"
  },
  {
    "timestamp": "2026-06-18T23:44:33.534Z",
    "status": "operational"
  },
  {
    "timestamp": "2026-06-18T23:45:42.577Z",
    "status": "outage"
  },
  {
    "timestamp": "2026-06-18T23:46:36.446Z",
    "status": "operational"
  },
  {
    "timestamp": "2026-06-18T23:49:33.534Z",
    "status": "operational"
  },
  {
    "timestamp": "2026-06-18T23:50:42.577Z",
    "status": "operational"
  },
  {
    "timestamp": "2026-06-18T23:51:36.446Z",
    "status": "outage"
  },
  {
    "timestamp": "2026-06-18T23:54:33.535Z",
    "status": "operational"
  },
  {
    "timestamp": "2026-06-18T23:55:42.638Z",
    "status": "operational"
  },
  {
    "timestamp": "2026-06-18T23:56:36.446Z",
    "status": "operational"
  },
  {
    "timestamp": "2026-06-18T23:59:33.534Z",
    "status": "operational"
  },
  {
    "timestamp": "2026-06-19T00:00:42.576Z",
    "status": "operational"
  },
  {
    "timestamp": "2026-06-19T00:01:36.447Z",
    "status": "operational"
  },
  {
    "timestamp": "2026-06-19T00:04:33.535Z",
    "status": "operational"
  },
  {
    "timestamp": "2026-06-19T00:05:42.577Z",
    "status": "operational"
  },
  {
    "timestamp": "2026-06-19T00:06:36.447Z",
    "status": "operational"
  },
  {
    "timestamp": "2026-06-19T00:09:33.536Z",
    "status": "operational"
  },
  {
    "timestamp": "2026-06-19T00:10:42.579Z",
    "status": "operational"
  },
  {
    "timestamp": "2026-06-19T00:11:36.447Z",
    "status": "operational"
  },
  {
    "timestamp": "2026-06-19T00:14:33.535Z",
    "status": "operational"
  },
  {
    "timestamp": "2026-06-19T00:15:42.579Z",
    "status": "operational"
  },
  {
    "timestamp": "2026-06-19T00:16:36.450Z",
    "status": "operational"
  },
  {
    "timestamp": "2026-06-19T00:19:33.534Z",
    "status": "operational"
  },
  {
    "timestamp": "2026-06-19T00:20:42.579Z",
    "status": "operational"
  },
  {
    "timestamp": "2026-06-19T00:21:36.450Z",
    "status": "operational"
  },
  {
    "timestamp": "2026-06-19T00:24:33.535Z",
    "status": "operational"
  },
  {
    "timestamp": "2026-06-19T00:25:42.701Z",
    "status": "operational"
  },
  {
    "timestamp": "2026-06-19T00:26:36.450Z",
    "status": "operational"
  },
  {
    "timestamp": "2026-06-19T00:29:33.538Z",
    "status": "operational"
  },
  {
    "timestamp": "2026-06-19T00:30:42.579Z",
    "status": "operational"
  },
  {
    "timestamp": "2026-06-19T00:31:36.450Z",
    "status": "operational"
  },
  {
    "timestamp": "2026-06-19T00:34:33.538Z",
    "status": "operational"
  },
  {
    "timestamp": "2026-06-19T00:35:42.579Z",
    "status": "operational"
  },
  {
    "timestamp": "2026-06-19T00:36:36.454Z",
    "status": "operational"
  },
  {
    "timestamp": "2026-06-19T00:39:33.537Z",
    "status": "operational"
  },
  {
    "timestamp": "2026-06-19T00:40:42.580Z",
    "status": "operational"
  },
  {
    "timestamp": "2026-06-19T00:41:36.456Z",
    "status": "operational"
  },
  {
    "timestamp": "2026-06-19T00:44:33.537Z",
    "status": "operational"
  },
  {
    "timestamp": "2026-06-19T00:45:42.579Z",
    "status": "operational"
  },
  {
    "timestamp": "2026-06-19T00:46:36.453Z",
    "status": "operational"
  },
  {
    "timestamp": "2026-06-19T00:49:33.537Z",
    "status": "operational"
  },
  {
    "timestamp": "2026-06-19T00:50:42.580Z",
    "status": "operational"
  },
  {
    "timestamp": "2026-06-19T00:51:36.454Z",
    "status": "operational"
  },
  {
    "timestamp": "2026-06-19T00:54:33.537Z",
    "status": "operational"
  },
  {
    "timestamp": "2026-06-19T00:55:42.578Z",
    "status": "operational"
  },
  {
    "timestamp": "2026-06-19T00:56:36.456Z",
    "status": "operational"
  },
  {
    "timestamp": "2026-06-19T00:59:33.537Z",
    "status": "operational"
  },
  {
    "timestamp": "2026-06-19T01:00:42.579Z",
    "status": "operational"
  },
  {
    "timestamp": "2026-06-19T01:01:36.454Z",
    "status": "operational"
  },
  {
    "timestamp": "2026-06-19T01:04:33.537Z",
    "status": "operational"
  },
  {
    "timestamp": "2026-06-19T01:05:42.579Z",
    "status": "operational"
  },
  {
    "timestamp": "2026-06-19T01:06:36.454Z",
    "status": "operational"
  },
  {
    "timestamp": "2026-06-19T01:09:33.537Z",
    "status": "operational"
  },
  {
    "timestamp": "2026-06-19T01:10:42.579Z",
    "status": "operational"
  },
  {
    "timestamp": "2026-06-19T01:11:36.455Z",
    "status": "operational"
  },
  {
    "timestamp": "2026-06-19T01:14:33.537Z",
    "status": "operational"
  },
  {
    "timestamp": "2026-06-19T01:15:42.642Z",
    "status": "operational"
  },
  {
    "timestamp": "2026-06-19T01:16:36.476Z",
    "status": "operational"
  },
  {
    "timestamp": "2026-06-19T01:19:33.537Z",
    "status": "operational"
  },
  {
    "timestamp": "2026-06-19T01:20:42.580Z",
    "status": "operational"
  },
  {
    "timestamp": "2026-06-19T01:21:36.458Z",
    "status": "operational"
  },
  {
    "timestamp": "2026-06-19T01:24:33.536Z",
    "status": "operational"
  },
  {
    "timestamp": "2026-06-19T01:25:42.579Z",
    "status": "operational"
  },
  {
    "timestamp": "2026-06-19T01:26:36.459Z",
    "status": "operational"
  },
  {
    "timestamp": "2026-06-19T01:29:33.536Z",
    "status": "operational"
  },
  {
    "timestamp": "2026-06-19T01:30:42.580Z",
    "status": "operational"
  },
  {
    "timestamp": "2026-06-19T01:31:36.455Z",
    "status": "operational"
  },
  {
    "timestamp": "2026-06-19T01:34:33.538Z",
    "status": "operational"
  },
  {
    "timestamp": "2026-06-19T01:35:42.580Z",
    "status": "operational"
  },
  {
    "timestamp": "2026-06-19T01:36:36.456Z",
    "status": "operational"
  },
  {
    "timestamp": "2026-06-19T01:39:33.537Z",
    "status": "operational"
  },
  {
    "timestamp": "2026-06-19T01:40:42.581Z",
    "status": "operational"
  },
  {
    "timestamp": "2026-06-19T01:41:36.455Z",
    "status": "operational"
  },
  {
    "timestamp": "2026-06-19T01:44:33.537Z",
    "status": "operational"
  },
  {
    "timestamp": "2026-06-19T01:45:42.581Z",
    "status": "operational"
  },
  {
    "timestamp": "2026-06-19T01:46:36.456Z",
    "status": "operational"
  },
  {
    "timestamp": "2026-06-19T01:49:33.537Z",
    "status": "operational"
  },
  {
    "timestamp": "2026-06-19T01:50:42.581Z",
    "status": "operational"
  },
  {
    "timestamp": "2026-06-19T01:51:36.456Z",
    "status": "operational"
  },
  {
    "timestamp": "2026-06-19T01:54:33.539Z",
    "status": "operational"
  },
  {
    "timestamp": "2026-06-19T01:55:42.584Z",
    "status": "operational"
  },
  {
    "timestamp": "2026-06-19T01:56:36.455Z",
    "status": "operational"
  },
  {
    "timestamp": "2026-06-19T01:59:33.538Z",
    "status": "operational"
  },
  {
    "timestamp": "2026-06-19T02:00:42.582Z",
    "status": "operational"
  },
  {
    "timestamp": "2026-06-19T02:01:36.455Z",
    "status": "operational"
  },
  {
    "timestamp": "2026-06-19T02:04:33.538Z",
    "status": "operational"
  },
  {
    "timestamp": "2026-06-19T02:05:42.582Z",
    "status": "operational"
  },
  {
    "timestamp": "2026-06-19T02:06:36.458Z",
    "status": "operational"
  },
  {
    "timestamp": "2026-06-19T02:09:33.538Z",
    "status": "operational"
  },
  {
    "timestamp": "2026-06-19T02:10:42.584Z",
    "status": "operational"
  },
  {
    "timestamp": "2026-06-19T02:11:36.459Z",
    "status": "operational"
  },
  {
    "timestamp": "2026-06-19T02:14:33.540Z",
    "status": "operational"
  },
  {
    "timestamp": "2026-06-19T02:15:42.583Z",
    "status": "operational"
  },
  {
    "timestamp": "2026-06-19T02:16:36.460Z",
    "status": "operational"
  },
  {
    "timestamp": "2026-06-19T02:19:33.538Z",
    "status": "operational"
  },
  {
    "timestamp": "2026-06-19T02:20:42.582Z",
    "status": "operational"
  },
  {
    "timestamp": "2026-06-19T02:21:36.463Z",
    "status": "operational"
  },
  {
    "timestamp": "2026-06-19T02:24:33.538Z",
    "status": "operational"
  },
  {
    "timestamp": "2026-06-19T02:25:42.619Z",
    "status": "operational"
  },
  {
    "timestamp": "2026-06-19T02:26:36.459Z",
    "status": "operational"
  },
  {
    "timestamp": "2026-06-19T02:29:33.537Z",
    "status": "operational"
  },
  {
    "timestamp": "2026-06-19T02:30:42.583Z",
    "status": "operational"
  },
  {
    "timestamp": "2026-06-19T02:31:36.459Z",
    "status": "operational"
  },
  {
    "timestamp": "2026-06-19T02:34:33.538Z",
    "status": "operational"
  },
  {
    "timestamp": "2026-06-19T02:35:42.583Z",
    "status": "operational"
  },
  {
    "timestamp": "2026-06-19T02:36:36.460Z",
    "status": "operational"
  },
  {
    "timestamp": "2026-06-19T02:39:33.538Z",
    "status": "operational"
  },
  {
    "timestamp": "2026-06-19T02:40:42.584Z",
    "status": "operational"
  },
  {
    "timestamp": "2026-06-19T02:41:36.462Z",
    "status": "operational"
  },
  {
    "timestamp": "2026-06-19T02:44:33.538Z",
    "status": "operational"
  },
  {
    "timestamp": "2026-06-19T02:45:42.583Z",
    "status": "operational"
  },
  {
    "timestamp": "2026-06-19T02:46:36.461Z",
    "status": "operational"
  },
  {
    "timestamp": "2026-06-19T02:49:33.539Z",
    "status": "operational"
  },
  {
    "timestamp": "2026-06-19T02:50:42.678Z",
    "status": "operational"
  },
  {
    "timestamp": "2026-06-19T02:51:36.460Z",
    "status": "operational"
  },
  {
    "timestamp": "2026-06-19T02:54:33.537Z",
    "status": "operational"
  },
  {
    "timestamp": "2026-06-19T02:55:42.583Z",
    "status": "operational"
  },
  {
    "timestamp": "2026-06-19T02:56:36.460Z",
    "status": "operational"
  },
  {
    "timestamp": "2026-06-19T02:59:33.538Z",
    "status": "operational"
  },
  {
    "timestamp": "2026-06-19T03:00:42.584Z",
    "status": "operational"
  },
  {
    "timestamp": "2026-06-19T03:01:36.460Z",
    "status": "operational"
  },
  {
    "timestamp": "2026-06-19T03:04:33.538Z",
    "status": "operational"
  },
  {
    "timestamp": "2026-06-19T03:05:42.584Z",
    "status": "operational"
  },
  {
    "timestamp": "2026-06-19T03:06:36.461Z",
    "status": "operational"
  },
  {
    "timestamp": "2026-06-19T03:09:33.539Z",
    "status": "operational"
  },
  {
    "timestamp": "2026-06-19T03:10:42.584Z",
    "status": "operational"
  },
  {
    "timestamp": "2026-06-19T03:11:36.460Z",
    "status": "operational"
  },
  {
    "timestamp": "2026-06-19T03:14:33.538Z",
    "status": "operational"
  },
  {
    "timestamp": "2026-06-19T03:15:42.583Z",
    "status": "operational"
  },
  {
    "timestamp": "2026-06-19T03:16:36.462Z",
    "status": "operational"
  },
  {
    "timestamp": "2026-06-19T03:19:33.540Z",
    "status": "operational"
  },
  {
    "timestamp": "2026-06-19T03:20:42.584Z",
    "status": "operational"
  },
  {
    "timestamp": "2026-06-19T03:21:36.461Z",
    "status": "operational"
  },
  {
    "timestamp": "2026-06-19T03:24:33.538Z",
    "status": "operational"
  },
  {
    "timestamp": "2026-06-19T03:25:42.615Z",
    "status": "operational"
  },
  {
    "timestamp": "2026-06-19T03:26:36.460Z",
    "status": "operational"
  },
  {
    "timestamp": "2026-06-19T03:29:33.537Z",
    "status": "operational"
  },
  {
    "timestamp": "2026-06-19T03:30:42.583Z",
    "status": "operational"
  },
  {
    "timestamp": "2026-06-19T03:31:36.460Z",
    "status": "operational"
  },
  {
    "timestamp": "2026-06-19T03:34:33.539Z",
    "status": "operational"
  },
  {
    "timestamp": "2026-06-19T03:35:42.583Z",
    "status": "operational"
  },
  {
    "timestamp": "2026-06-19T03:41:23.944Z",
    "status": "operational"
  },
  {
    "timestamp": "2026-06-19T03:41:33.073Z",
    "status": "operational"
  },
  {
    "timestamp": "2026-06-19T03:41:42.207Z",
    "status": "operational"
  },
  {
    "timestamp": "2026-06-19T03:46:23.934Z",
    "status": "operational"
  },
  {
    "timestamp": "2026-06-19T03:46:33.066Z",
    "status": "operational"
  },
  {
    "timestamp": "2026-06-19T03:46:42.206Z",
    "status": "operational"
  },
  {
    "timestamp": "2026-06-19T03:51:23.933Z",
    "status": "operational"
  },
  {
    "timestamp": "2026-06-19T03:51:33.067Z",
    "status": "operational"
  },
  {
    "timestamp": "2026-06-19T03:51:42.205Z",
    "status": "operational"
  },
  {
    "timestamp": "2026-06-19T03:56:23.933Z",
    "status": "operational"
  },
  {
    "timestamp": "2026-06-19T03:56:33.066Z",
    "status": "operational"
  },
  {
    "timestamp": "2026-06-19T03:56:42.204Z",
    "status": "operational"
  },
  {
    "timestamp": "2026-06-19T04:01:23.936Z",
    "status": "operational"
  },
  {
    "timestamp": "2026-06-19T04:01:33.070Z",
    "status": "operational"
  },
  {
    "timestamp": "2026-06-19T04:01:42.206Z",
    "status": "operational"
  },
  {
    "timestamp": "2026-06-19T04:06:23.937Z",
    "status": "operational"
  },
  {
    "timestamp": "2026-06-19T04:06:33.070Z",
    "status": "operational"
  },
  {
    "timestamp": "2026-06-19T04:06:42.208Z",
    "status": "operational"
  },
  {
    "timestamp": "2026-06-19T04:11:23.942Z",
    "status": "operational"
  },
  {
    "timestamp": "2026-06-19T04:11:33.070Z",
    "status": "operational"
  },
  {
    "timestamp": "2026-06-19T04:11:42.209Z",
    "status": "operational"
  },
  {
    "timestamp": "2026-06-19T04:16:23.942Z",
    "status": "operational"
  },
  {
    "timestamp": "2026-06-19T04:16:33.071Z",
    "status": "operational"
  },
  {
    "timestamp": "2026-06-19T04:16:42.208Z",
    "status": "operational"
  },
  {
    "timestamp": "2026-06-19T04:21:23.950Z",
    "status": "operational"
  },
  {
    "timestamp": "2026-06-19T04:21:33.071Z",
    "status": "operational"
  },
  {
    "timestamp": "2026-06-19T04:21:42.209Z",
    "status": "operational"
  },
  {
    "timestamp": "2026-06-19T04:26:23.944Z",
    "status": "operational"
  },
  {
    "timestamp": "2026-06-19T04:26:33.071Z",
    "status": "operational"
  },
  {
    "timestamp": "2026-06-19T04:26:42.208Z",
    "status": "operational"
  },
  {
    "timestamp": "2026-06-19T04:31:23.944Z",
    "status": "operational"
  },
  {
    "timestamp": "2026-06-19T04:31:33.074Z",
    "status": "operational"
  },
  {
    "timestamp": "2026-06-19T04:31:42.211Z",
    "status": "operational"
  },
  {
    "timestamp": "2026-06-19T04:36:23.947Z",
    "status": "operational"
  },
  {
    "timestamp": "2026-06-19T04:36:33.074Z",
    "status": "operational"
  },
  {
    "timestamp": "2026-06-19T04:36:42.211Z",
    "status": "operational"
  },
  {
    "timestamp": "2026-06-19T04:41:23.947Z",
    "status": "operational"
  },
  {
    "timestamp": "2026-06-19T04:41:33.074Z",
    "status": "operational"
  },
  {
    "timestamp": "2026-06-19T04:41:42.210Z",
    "status": "operational"
  }
]