[
  {
    "timestamp": "2026-06-07T14:07:49.311Z",
    "status": "outage"
  },
  {
    "timestamp": "2026-06-07T14:08:57.514Z",
    "status": "operational"
  },
  {
    "timestamp": "2026-06-07T14:09:14.012Z",
    "status": "operational"
  },
  {
    "timestamp": "2026-06-07T14:09:54.085Z",
    "status": "operational"
  },
  {
    "timestamp": "2026-06-07T14:10:36.129Z",
    "status": "operational"
  },
  {
    "timestamp": "2026-06-07T14:12:49.315Z",
    "status": "outage"
  },
  {
    "timestamp": "2026-06-07T14:13:57.510Z",
    "status": "operational"
  },
  {
    "timestamp": "2026-06-07T14:14:14.016Z",
    "status": "operational"
  },
  {
    "timestamp": "2026-06-07T14:14:54.086Z",
    "status": "operational"
  },
  {
    "timestamp": "2026-06-07T14:15:36.122Z",
    "status": "operational"
  },
  {
    "timestamp": "2026-06-07T14:17:49.315Z",
    "status": "outage"
  },
  {
    "timestamp": "2026-06-07T14:18:57.510Z",
    "status": "operational"
  },
  {
    "timestamp": "2026-06-07T14:19:14.015Z",
    "status": "operational"
  },
  {
    "timestamp": "2026-06-07T14:19:54.084Z",
    "status": "operational"
  },
  {
    "timestamp": "2026-06-07T14:20:36.125Z",
    "status": "operational"
  },
  {
    "timestamp": "2026-06-07T14:22:49.320Z",
    "status": "outage"
  },
  {
    "timestamp": "2026-06-07T14:23:57.510Z",
    "status": "operational"
  },
  {
    "timestamp": "2026-06-07T14:24:14.019Z",
    "status": "operational"
  },
  {
    "timestamp": "2026-06-07T14:24:54.086Z",
    "status": "operational"
  },
  {
    "timestamp": "2026-06-07T14:25:36.125Z",
    "status": "operational"
  },
  {
    "timestamp": "2026-06-07T14:27:49.321Z",
    "status": "outage"
  },
  {
    "timestamp": "2026-06-07T14:28:57.517Z",
    "status": "operational"
  },
  {
    "timestamp": "2026-06-07T14:29:14.020Z",
    "status": "operational"
  },
  {
    "timestamp": "2026-06-07T14:29:54.088Z",
    "status": "operational"
  },
  {
    "timestamp": "2026-06-07T14:30:36.129Z",
    "status": "operational"
  },
  {
    "timestamp": "2026-06-07T14:32:49.325Z",
    "status": "outage"
  },
  {
    "timestamp": "2026-06-07T14:33:57.515Z",
    "status": "operational"
  },
  {
    "timestamp": "2026-06-07T14:34:14.023Z",
    "status": "operational"
  },
  {
    "timestamp": "2026-06-07T14:34:54.089Z",
    "status": "operational"
  },
  {
    "timestamp": "2026-06-07T14:35:36.130Z",
    "status": "operational"
  },
  {
    "timestamp": "2026-06-07T14:37:49.329Z",
    "status": "outage"
  },
  {
    "timestamp": "2026-06-07T14:38:57.514Z",
    "status": "operational"
  },
  {
    "timestamp": "2026-06-07T14:39:14.025Z",
    "status": "operational"
  },
  {
    "timestamp": "2026-06-07T14:39:54.088Z",
    "status": "operational"
  },
  {
    "timestamp": "2026-06-07T14:40:36.128Z",
    "status": "operational"
  },
  {
    "timestamp": "2026-06-07T14:42:49.333Z",
    "status": "outage"
  },
  {
    "timestamp": "2026-06-07T14:43:57.517Z",
    "status": "operational"
  },
  {
    "timestamp": "2026-06-07T14:44:14.026Z",
    "status": "operational"
  },
  {
    "timestamp": "2026-06-07T14:44:54.089Z",
    "status": "operational"
  },
  {
    "timestamp": "2026-06-07T14:45:36.129Z",
    "status": "operational"
  },
  {
    "timestamp": "2026-06-07T14:47:49.333Z",
    "status": "outage"
  },
  {
    "timestamp": "2026-06-07T14:48:57.518Z",
    "status": "operational"
  },
  {
    "timestamp": "2026-06-07T14:49:14.027Z",
    "status": "operational"
  },
  {
    "timestamp": "2026-06-07T14:49:54.090Z",
    "status": "operational"
  },
  {
    "timestamp": "2026-06-07T14:50:36.129Z",
    "status": "operational"
  },
  {
    "timestamp": "2026-06-07T14:52:49.336Z",
    "status": "outage"
  },
  {
    "timestamp": "2026-06-07T14:53:57.517Z",
    "status": "operational"
  },
  {
    "timestamp": "2026-06-07T14:54:14.029Z",
    "status": "operational"
  },
  {
    "timestamp": "2026-06-07T14:54:54.091Z",
    "status": "operational"
  },
  {
    "timestamp": "2026-06-07T14:55:36.131Z",
    "status": "operational"
  },
  {
    "timestamp": "2026-06-07T14:57:49.337Z",
    "status": "outage"
  },
  {
    "timestamp": "2026-06-07T14:58:57.518Z",
    "status": "operational"
  },
  {
    "timestamp": "2026-06-07T14:59:14.030Z",
    "status": "operational"
  },
  {
    "timestamp": "2026-06-07T14:59:54.090Z",
    "status": "operational"
  },
  {
    "timestamp": "2026-06-07T15:00:36.213Z",
    "status": "operational"
  },
  {
    "timestamp": "2026-06-07T15:02:49.341Z",
    "status": "outage"
  },
  {
    "timestamp": "2026-06-07T15:03:57.524Z",
    "status": "operational"
  },
  {
    "timestamp": "2026-06-07T15:04:14.031Z",
    "status": "operational"
  },
  {
    "timestamp": "2026-06-07T15:04:54.090Z",
    "status": "operational"
  },
  {
    "timestamp": "2026-06-07T15:05:36.135Z",
    "status": "operational"
  },
  {
    "timestamp": "2026-06-07T15:07:49.341Z",
    "status": "outage"
  },
  {
    "timestamp": "2026-06-07T15:08:57.525Z",
    "status": "operational"
  },
  {
    "timestamp": "2026-06-07T15:09:14.031Z",
    "status": "operational"
  },
  {
    "timestamp": "2026-06-07T15:09:54.094Z",
    "status": "operational"
  },
  {
    "timestamp": "2026-06-07T15:10:36.132Z",
    "status": "operational"
  },
  {
    "timestamp": "2026-06-07T15:12:49.344Z",
    "status": "outage"
  },
  {
    "timestamp": "2026-06-07T15:13:57.528Z",
    "status": "operational"
  },
  {
    "timestamp": "2026-06-07T15:14:14.032Z",
    "status": "operational"
  },
  {
    "timestamp": "2026-06-07T15:14:54.098Z",
    "status": "operational"
  },
  {
    "timestamp": "2026-06-07T15:15:36.134Z",
    "status": "operational"
  },
  {
    "timestamp": "2026-06-07T15:17:49.345Z",
    "status": "outage"
  },
  {
    "timestamp": "2026-06-07T15:18:57.534Z",
    "status": "operational"
  },
  {
    "timestamp": "2026-06-07T15:19:14.030Z",
    "status": "operational"
  },
  {
    "timestamp": "2026-06-07T15:19:54.103Z",
    "status": "operational"
  },
  {
    "timestamp": "2026-06-07T15:20:36.136Z",
    "status": "operational"
  },
  {
    "timestamp": "2026-06-07T15:22:49.346Z",
    "status": "outage"
  },
  {
    "timestamp": "2026-06-07T15:23:57.537Z",
    "status": "operational"
  },
  {
    "timestamp": "2026-06-07T15:24:14.037Z",
    "status": "operational"
  },
  {
    "timestamp": "2026-06-07T15:24:54.105Z",
    "status": "operational"
  },
  {
    "timestamp": "2026-06-07T15:25:36.138Z",
    "status": "operational"
  },
  {
    "timestamp": "2026-06-07T15:27:49.347Z",
    "status": "outage"
  },
  {
    "timestamp": "2026-06-07T15:28:57.537Z",
    "status": "operational"
  },
  {
    "timestamp": "2026-06-07T15:29:14.036Z",
    "status": "operational"
  },
  {
    "timestamp": "2026-06-07T15:29:54.109Z",
    "status": "operational"
  },
  {
    "timestamp": "2026-06-07T15:30:36.140Z",
    "status": "operational"
  },
  {
    "timestamp": "2026-06-07T15:32:49.347Z",
    "status": "outage"
  },
  {
    "timestamp": "2026-06-07T15:33:57.540Z",
    "status": "operational"
  },
  {
    "timestamp": "2026-06-07T15:34:14.042Z",
    "status": "operational"
  },
  {
    "timestamp": "2026-06-07T15:34:54.110Z",
    "status": "operational"
  },
  {
    "timestamp": "2026-06-07T15:35:36.140Z",
    "status": "operational"
  },
  {
    "timestamp": "2026-06-07T15:37:49.348Z",
    "status": "outage"
  },
  {
    "timestamp": "2026-06-07T15:38:57.546Z",
    "status": "operational"
  },
  {
    "timestamp": "2026-06-07T15:39:14.046Z",
    "status": "operational"
  },
  {
    "timestamp": "2026-06-07T15:39:54.112Z",
    "status": "operational"
  },
  {
    "timestamp": "2026-06-07T15:40:36.143Z",
    "status": "operational"
  },
  {
    "timestamp": "2026-06-07T15:42:49.350Z",
    "status": "outage"
  },
  {
    "timestamp": "2026-06-07T15:43:57.551Z",
    "status": "operational"
  },
  {
    "timestamp": "2026-06-07T15:44:14.050Z",
    "status": "operational"
  },
  {
    "timestamp": "2026-06-07T15:44:54.114Z",
    "status": "operational"
  },
  {
    "timestamp": "2026-06-07T15:45:36.144Z",
    "status": "operational"
  },
  {
    "timestamp": "2026-06-07T15:47:49.351Z",
    "status": "outage"
  },
  {
    "timestamp": "2026-06-07T15:48:57.558Z",
    "status": "operational"
  },
  {
    "timestamp": "2026-06-07T15:49:14.054Z",
    "status": "operational"
  },
  {
    "timestamp": "2026-06-07T15:49:54.115Z",
    "status": "operational"
  },
  {
    "timestamp": "2026-06-07T15:50:36.145Z",
    "status": "operational"
  },
  {
    "timestamp": "2026-06-07T15:52:49.352Z",
    "status": "outage"
  },
  {
    "timestamp": "2026-06-07T15:53:57.556Z",
    "status": "operational"
  },
  {
    "timestamp": "2026-06-07T15:54:14.058Z",
    "status": "operational"
  },
  {
    "timestamp": "2026-06-07T15:54:54.116Z",
    "status": "operational"
  },
  {
    "timestamp": "2026-06-07T15:55:36.146Z",
    "status": "operational"
  },
  {
    "timestamp": "2026-06-07T15:57:49.352Z",
    "status": "outage"
  },
  {
    "timestamp": "2026-06-07T15:58:57.556Z",
    "status": "operational"
  },
  {
    "timestamp": "2026-06-07T15:59:14.058Z",
    "status": "operational"
  },
  {
    "timestamp": "2026-06-07T15:59:54.118Z",
    "status": "operational"
  },
  {
    "timestamp": "2026-06-07T16:00:36.146Z",
    "status": "operational"
  },
  {
    "timestamp": "2026-06-07T16:02:49.354Z",
    "status": "outage"
  },
  {
    "timestamp": "2026-06-07T16:03:57.558Z",
    "status": "operational"
  },
  {
    "timestamp": "2026-06-07T16:04:14.061Z",
    "status": "degraded"
  },
  {
    "timestamp": "2026-06-07T16:04:54.118Z",
    "status": "operational"
  },
  {
    "timestamp": "2026-06-07T16:05:36.147Z",
    "status": "operational"
  },
  {
    "timestamp": "2026-06-07T16:07:49.354Z",
    "status": "outage"
  },
  {
    "timestamp": "2026-06-07T16:08:57.572Z",
    "status": "operational"
  },
  {
    "timestamp": "2026-06-07T16:09:14.064Z",
    "status": "operational"
  },
  {
    "timestamp": "2026-06-07T16:09:54.120Z",
    "status": "operational"
  },
  {
    "timestamp": "2026-06-07T16:10:36.147Z",
    "status": "operational"
  },
  {
    "timestamp": "2026-06-07T16:12:49.354Z",
    "status": "outage"
  },
  {
    "timestamp": "2026-06-07T16:13:57.562Z",
    "status": "operational"
  },
  {
    "timestamp": "2026-06-07T16:14:14.067Z",
    "status": "operational"
  },
  {
    "timestamp": "2026-06-07T16:14:54.123Z",
    "status": "operational"
  },
  {
    "timestamp": "2026-06-07T16:15:36.147Z",
    "status": "operational"
  },
  {
    "timestamp": "2026-06-07T16:17:49.354Z",
    "status": "outage"
  },
  {
    "timestamp": "2026-06-07T16:18:57.564Z",
    "status": "operational"
  },
  {
    "timestamp": "2026-06-07T16:19:14.070Z",
    "status": "operational"
  },
  {
    "timestamp": "2026-06-07T16:19:54.127Z",
    "status": "operational"
  },
  {
    "timestamp": "2026-06-07T16:20:36.148Z",
    "status": "operational"
  },
  {
    "timestamp": "2026-06-07T16:22:49.354Z",
    "status": "outage"
  },
  {
    "timestamp": "2026-06-07T16:23:57.567Z",
    "status": "operational"
  },
  {
    "timestamp": "2026-06-07T16:24:14.073Z",
    "status": "operational"
  },
  {
    "timestamp": "2026-06-07T16:24:54.128Z",
    "status": "operational"
  },
  {
    "timestamp": "2026-06-07T16:25:36.148Z",
    "status": "operational"
  },
  {
    "timestamp": "2026-06-07T16:27:49.358Z",
    "status": "outage"
  },
  {
    "timestamp": "2026-06-07T16:28:57.567Z",
    "status": "operational"
  },
  {
    "timestamp": "2026-06-07T16:29:14.073Z",
    "status": "operational"
  },
  {
    "timestamp": "2026-06-07T16:29:54.131Z",
    "status": "operational"
  },
  {
    "timestamp": "2026-06-07T16:30:36.149Z",
    "status": "operational"
  },
  {
    "timestamp": "2026-06-07T16:32:49.362Z",
    "status": "outage"
  },
  {
    "timestamp": "2026-06-07T16:33:57.568Z",
    "status": "operational"
  },
  {
    "timestamp": "2026-06-07T16:34:14.075Z",
    "status": "operational"
  },
  {
    "timestamp": "2026-06-07T16:34:54.131Z",
    "status": "operational"
  },
  {
    "timestamp": "2026-06-07T16:35:36.150Z",
    "status": "operational"
  },
  {
    "timestamp": "2026-06-07T16:37:49.365Z",
    "status": "outage"
  },
  {
    "timestamp": "2026-06-07T16:38:57.568Z",
    "status": "operational"
  },
  {
    "timestamp": "2026-06-07T16:39:14.078Z",
    "status": "operational"
  },
  {
    "timestamp": "2026-06-07T16:39:54.134Z",
    "status": "operational"
  },
  {
    "timestamp": "2026-06-07T16:40:36.149Z",
    "status": "operational"
  },
  {
    "timestamp": "2026-06-07T16:42:49.370Z",
    "status": "outage"
  },
  {
    "timestamp": "2026-06-07T16:43:57.566Z",
    "status": "operational"
  },
  {
    "timestamp": "2026-06-07T16:44:14.079Z",
    "status": "operational"
  },
  {
    "timestamp": "2026-06-07T16:44:54.137Z",
    "status": "operational"
  },
  {
    "timestamp": "2026-06-07T16:45:36.151Z",
    "status": "operational"
  },
  {
    "timestamp": "2026-06-07T16:47:49.372Z",
    "status": "outage"
  },
  {
    "timestamp": "2026-06-07T16:48:57.572Z",
    "status": "operational"
  },
  {
    "timestamp": "2026-06-07T16:49:14.081Z",
    "status": "operational"
  },
  {
    "timestamp": "2026-06-07T16:49:54.143Z",
    "status": "operational"
  },
  {
    "timestamp": "2026-06-07T16:50:36.152Z",
    "status": "operational"
  },
  {
    "timestamp": "2026-06-07T16:52:49.373Z",
    "status": "outage"
  },
  {
    "timestamp": "2026-06-07T16:53:57.569Z",
    "status": "operational"
  },
  {
    "timestamp": "2026-06-07T16:54:14.081Z",
    "status": "operational"
  },
  {
    "timestamp": "2026-06-07T16:54:54.140Z",
    "status": "operational"
  },
  {
    "timestamp": "2026-06-07T16:55:36.152Z",
    "status": "operational"
  },
  {
    "timestamp": "2026-06-07T16:57:49.376Z",
    "status": "outage"
  },
  {
    "timestamp": "2026-06-07T16:58:57.570Z",
    "status": "operational"
  },
  {
    "timestamp": "2026-06-07T16:59:14.081Z",
    "status": "operational"
  },
  {
    "timestamp": "2026-06-07T16:59:54.141Z",
    "status": "operational"
  },
  {
    "timestamp": "2026-06-07T17:00:36.152Z",
    "status": "operational"
  },
  {
    "timestamp": "2026-06-07T17:02:49.379Z",
    "status": "outage"
  },
  {
    "timestamp": "2026-06-07T17:03:57.570Z",
    "status": "operational"
  },
  {
    "timestamp": "2026-06-07T17:04:14.082Z",
    "status": "operational"
  },
  {
    "timestamp": "2026-06-07T17:04:54.142Z",
    "status": "operational"
  },
  {
    "timestamp": "2026-06-07T17:05:36.154Z",
    "status": "operational"
  },
  {
    "timestamp": "2026-06-07T17:07:49.382Z",
    "status": "outage"
  },
  {
    "timestamp": "2026-06-07T17:08:57.573Z",
    "status": "operational"
  },
  {
    "timestamp": "2026-06-07T17:09:14.082Z",
    "status": "operational"
  },
  {
    "timestamp": "2026-06-07T17:09:54.144Z",
    "status": "operational"
  },
  {
    "timestamp": "2026-06-07T17:10:36.154Z",
    "status": "operational"
  },
  {
    "timestamp": "2026-06-07T17:12:49.384Z",
    "status": "outage"
  },
  {
    "timestamp": "2026-06-07T17:13:57.571Z",
    "status": "operational"
  },
  {
    "timestamp": "2026-06-07T17:14:14.083Z",
    "status": "operational"
  },
  {
    "timestamp": "2026-06-07T17:14:54.145Z",
    "status": "operational"
  },
  {
    "timestamp": "2026-06-07T17:15:36.156Z",
    "status": "operational"
  },
  {
    "timestamp": "2026-06-07T17:17:49.384Z",
    "status": "outage"
  },
  {
    "timestamp": "2026-06-07T17:18:57.575Z",
    "status": "operational"
  },
  {
    "timestamp": "2026-06-07T17:19:14.084Z",
    "status": "operational"
  },
  {
    "timestamp": "2026-06-07T17:19:54.148Z",
    "status": "operational"
  },
  {
    "timestamp": "2026-06-07T17:20:36.157Z",
    "status": "operational"
  },
  {
    "timestamp": "2026-06-07T17:22:49.386Z",
    "status": "outage"
  },
  {
    "timestamp": "2026-06-07T17:23:57.580Z",
    "status": "operational"
  },
  {
    "timestamp": "2026-06-07T17:24:14.086Z",
    "status": "operational"
  },
  {
    "timestamp": "2026-06-07T17:24:54.148Z",
    "status": "operational"
  },
  {
    "timestamp": "2026-06-07T17:25:36.159Z",
    "status": "operational"
  },
  {
    "timestamp": "2026-06-07T17:27:49.387Z",
    "status": "outage"
  },
  {
    "timestamp": "2026-06-07T17:28:57.582Z",
    "status": "operational"
  },
  {
    "timestamp": "2026-06-07T17:29:14.085Z",
    "status": "operational"
  },
  {
    "timestamp": "2026-06-07T17:29:54.151Z",
    "status": "operational"
  },
  {
    "timestamp": "2026-06-07T17:30:36.159Z",
    "status": "outage"
  },
  {
    "timestamp": "2026-06-07T17:32:49.388Z",
    "status": "outage"
  },
  {
    "timestamp": "2026-06-07T17:33:57.584Z",
    "status": "operational"
  },
  {
    "timestamp": "2026-06-07T17:34:14.090Z",
    "status": "operational"
  },
  {
    "timestamp": "2026-06-07T17:34:54.148Z",
    "status": "operational"
  },
  {
    "timestamp": "2026-06-07T17:35:36.159Z",
    "status": "operational"
  },
  {
    "timestamp": "2026-06-07T17:37:49.389Z",
    "status": "outage"
  },
  {
    "timestamp": "2026-06-07T17:38:57.588Z",
    "status": "operational"
  },
  {
    "timestamp": "2026-06-07T17:39:14.095Z",
    "status": "operational"
  },
  {
    "timestamp": "2026-06-07T17:39:54.151Z",
    "status": "operational"
  },
  {
    "timestamp": "2026-06-07T17:40:36.160Z",
    "status": "operational"
  },
  {
    "timestamp": "2026-06-07T17:42:49.389Z",
    "status": "outage"
  },
  {
    "timestamp": "2026-06-07T17:43:57.591Z",
    "status": "operational"
  },
  {
    "timestamp": "2026-06-07T17:44:14.099Z",
    "status": "operational"
  },
  {
    "timestamp": "2026-06-07T17:44:54.152Z",
    "status": "operational"
  },
  {
    "timestamp": "2026-06-07T17:45:36.162Z",
    "status": "operational"
  },
  {
    "timestamp": "2026-06-07T17:47:49.391Z",
    "status": "outage"
  },
  {
    "timestamp": "2026-06-07T17:48:57.600Z",
    "status": "operational"
  },
  {
    "timestamp": "2026-06-07T17:49:14.104Z",
    "status": "operational"
  },
  {
    "timestamp": "2026-06-07T17:49:54.152Z",
    "status": "operational"
  },
  {
    "timestamp": "2026-06-07T17:50:36.162Z",
    "status": "operational"
  },
  {
    "timestamp": "2026-06-07T17:52:49.392Z",
    "status": "outage"
  },
  {
    "timestamp": "2026-06-07T17:53:57.596Z",
    "status": "operational"
  },
  {
    "timestamp": "2026-06-07T17:54:14.106Z",
    "status": "operational"
  },
  {
    "timestamp": "2026-06-07T17:54:54.154Z",
    "status": "operational"
  },
  {
    "timestamp": "2026-06-07T17:55:36.163Z",
    "status": "operational"
  },
  {
    "timestamp": "2026-06-07T17:57:49.394Z",
    "status": "outage"
  },
  {
    "timestamp": "2026-06-07T17:58:57.598Z",
    "status": "operational"
  },
  {
    "timestamp": "2026-06-07T17:59:14.107Z",
    "status": "operational"
  },
  {
    "timestamp": "2026-06-07T17:59:54.152Z",
    "status": "operational"
  },
  {
    "timestamp": "2026-06-07T18:00:36.168Z",
    "status": "operational"
  },
  {
    "timestamp": "2026-06-07T18:02:49.397Z",
    "status": "outage"
  },
  {
    "timestamp": "2026-06-07T18:03:57.601Z",
    "status": "operational"
  },
  {
    "timestamp": "2026-06-07T18:04:14.111Z",
    "status": "operational"
  },
  {
    "timestamp": "2026-06-07T18:04:54.154Z",
    "status": "operational"
  },
  {
    "timestamp": "2026-06-07T18:05:36.167Z",
    "status": "operational"
  },
  {
    "timestamp": "2026-06-07T18:07:49.397Z",
    "status": "outage"
  },
  {
    "timestamp": "2026-06-07T18:08:57.601Z",
    "status": "operational"
  },
  {
    "timestamp": "2026-06-07T18:09:14.110Z",
    "status": "operational"
  },
  {
    "timestamp": "2026-06-07T18:09:54.153Z",
    "status": "operational"
  },
  {
    "timestamp": "2026-06-07T18:10:36.170Z",
    "status": "operational"
  },
  {
    "timestamp": "2026-06-07T18:12:49.399Z",
    "status": "outage"
  },
  {
    "timestamp": "2026-06-07T18:13:57.605Z",
    "status": "operational"
  },
  {
    "timestamp": "2026-06-07T18:14:14.115Z",
    "status": "operational"
  },
  {
    "timestamp": "2026-06-07T18:14:54.154Z",
    "status": "operational"
  },
  {
    "timestamp": "2026-06-07T18:15:36.170Z",
    "status": "operational"
  },
  {
    "timestamp": "2026-06-07T18:17:49.399Z",
    "status": "outage"
  },
  {
    "timestamp": "2026-06-07T18:18:57.604Z",
    "status": "operational"
  },
  {
    "timestamp": "2026-06-07T18:19:14.119Z",
    "status": "operational"
  },
  {
    "timestamp": "2026-06-07T18:19:54.160Z",
    "status": "operational"
  },
  {
    "timestamp": "2026-06-07T18:20:36.171Z",
    "status": "operational"
  },
  {
    "timestamp": "2026-06-07T18:22:49.400Z",
    "status": "outage"
  },
  {
    "timestamp": "2026-06-07T18:23:57.606Z",
    "status": "operational"
  },
  {
    "timestamp": "2026-06-07T18:24:14.122Z",
    "status": "operational"
  },
  {
    "timestamp": "2026-06-07T18:24:54.164Z",
    "status": "operational"
  },
  {
    "timestamp": "2026-06-07T18:25:36.169Z",
    "status": "operational"
  },
  {
    "timestamp": "2026-06-07T18:27:49.401Z",
    "status": "outage"
  },
  {
    "timestamp": "2026-06-07T18:28:57.608Z",
    "status": "operational"
  },
  {
    "timestamp": "2026-06-07T18:29:14.123Z",
    "status": "operational"
  },
  {
    "timestamp": "2026-06-07T18:29:54.169Z",
    "status": "operational"
  },
  {
    "timestamp": "2026-06-07T18:30:36.169Z",
    "status": "operational"
  },
  {
    "timestamp": "2026-06-07T18:32:49.403Z",
    "status": "outage"
  },
  {
    "timestamp": "2026-06-07T18:33:57.609Z",
    "status": "operational"
  },
  {
    "timestamp": "2026-06-07T18:34:14.126Z",
    "status": "operational"
  },
  {
    "timestamp": "2026-06-07T18:34:54.167Z",
    "status": "operational"
  },
  {
    "timestamp": "2026-06-07T18:35:36.169Z",
    "status": "operational"
  },
  {
    "timestamp": "2026-06-07T18:37:49.403Z",
    "status": "outage"
  },
  {
    "timestamp": "2026-06-07T18:38:57.611Z",
    "status": "operational"
  },
  {
    "timestamp": "2026-06-07T18:39:14.128Z",
    "status": "operational"
  },
  {
    "timestamp": "2026-06-07T18:39:54.170Z",
    "status": "operational"
  },
  {
    "timestamp": "2026-06-07T18:40:36.170Z",
    "status": "operational"
  },
  {
    "timestamp": "2026-06-07T18:42:49.403Z",
    "status": "outage"
  },
  {
    "timestamp": "2026-06-07T18:43:57.613Z",
    "status": "operational"
  },
  {
    "timestamp": "2026-06-07T18:44:14.131Z",
    "status": "operational"
  },
  {
    "timestamp": "2026-06-07T18:44:54.172Z",
    "status": "operational"
  },
  {
    "timestamp": "2026-06-07T18:45:36.170Z",
    "status": "operational"
  },
  {
    "timestamp": "2026-06-07T18:47:49.403Z",
    "status": "outage"
  },
  {
    "timestamp": "2026-06-07T18:48:57.616Z",
    "status": "operational"
  },
  {
    "timestamp": "2026-06-07T18:49:14.132Z",
    "status": "operational"
  },
  {
    "timestamp": "2026-06-07T18:49:54.176Z",
    "status": "operational"
  },
  {
    "timestamp": "2026-06-07T18:50:36.170Z",
    "status": "operational"
  },
  {
    "timestamp": "2026-06-07T18:52:49.406Z",
    "status": "outage"
  },
  {
    "timestamp": "2026-06-07T18:53:57.615Z",
    "status": "operational"
  },
  {
    "timestamp": "2026-06-07T18:54:14.134Z",
    "status": "operational"
  }
]