[
  {
    "timestamp": "2026-05-23T01:03:40Z",
    "status": "operational"
  },
  {
    "timestamp": "2026-05-23T01:04:20Z",
    "status": "degraded"
  },
  {
    "timestamp": "2026-05-23T01:05:28Z",
    "status": "operational"
  },
  {
    "timestamp": "2026-05-23T01:06:15Z",
    "status": "operational"
  },
  {
    "timestamp": "2026-05-23T01:11:17Z",
    "status": "degraded"
  },
  {
    "timestamp": "2026-05-23T01:16:37Z",
    "status": "degraded"
  },
  {
    "timestamp": "2026-05-23T01:21:38Z",
    "status": "operational"
  },
  {
    "timestamp": "2026-05-23T01:26:59Z",
    "status": "operational"
  },
  {
    "timestamp": "2026-05-23T01:32:02Z",
    "status": "operational"
  },
  {
    "timestamp": "2026-05-23T01:37:04Z",
    "status": "operational"
  },
  {
    "timestamp": "2026-05-23T01:42:06Z",
    "status": "operational"
  },
  {
    "timestamp": "2026-05-23T01:47:07Z",
    "status": "operational"
  },
  {
    "timestamp": "2026-05-23T01:52:09Z",
    "status": "operational"
  },
  {
    "timestamp": "2026-05-23T01:57:11Z",
    "status": "operational"
  },
  {
    "timestamp": "2026-05-23T02:02:13Z",
    "status": "operational"
  },
  {
    "timestamp": "2026-05-23T02:07:15Z",
    "status": "operational"
  },
  {
    "timestamp": "2026-05-23T02:12:16Z",
    "status": "operational"
  },
  {
    "timestamp": "2026-05-23T02:17:18Z",
    "status": "operational"
  },
  {
    "timestamp": "2026-05-23T02:22:20Z",
    "status": "operational"
  },
  {
    "timestamp": "2026-05-23T02:27:21Z",
    "status": "operational"
  },
  {
    "timestamp": "2026-05-23T02:32:23Z",
    "status": "operational"
  },
  {
    "timestamp": "2026-05-23T02:37:24Z",
    "status": "operational"
  },
  {
    "timestamp": "2026-05-23T02:42:26Z",
    "status": "operational"
  },
  {
    "timestamp": "2026-05-23T02:47:28Z",
    "status": "operational"
  },
  {
    "timestamp": "2026-05-23T02:52:29Z",
    "status": "operational"
  },
  {
    "timestamp": "2026-05-23T02:57:31Z",
    "status": "operational"
  },
  {
    "timestamp": "2026-05-23T03:02:32Z",
    "status": "operational"
  },
  {
    "timestamp": "2026-05-23T03:07:34Z",
    "status": "operational"
  },
  {
    "timestamp": "2026-05-23T03:12:36Z",
    "status": "operational"
  },
  {
    "timestamp": "2026-05-23T03:17:37Z",
    "status": "operational"
  },
  {
    "timestamp": "2026-05-23T03:22:39Z",
    "status": "operational"
  },
  {
    "timestamp": "2026-05-23T03:27:40Z",
    "status": "operational"
  },
  {
    "timestamp": "2026-05-23T03:32:42Z",
    "status": "operational"
  },
  {
    "timestamp": "2026-05-23T03:37:44Z",
    "status": "operational"
  },
  {
    "timestamp": "2026-05-23T03:42:45Z",
    "status": "operational"
  },
  {
    "timestamp": "2026-05-23T03:47:47Z",
    "status": "operational"
  },
  {
    "timestamp": "2026-05-23T03:52:49Z",
    "status": "operational"
  },
  {
    "timestamp": "2026-05-23T03:57:50Z",
    "status": "operational"
  },
  {
    "timestamp": "2026-05-23T04:02:52Z",
    "status": "operational"
  },
  {
    "timestamp": "2026-05-23T04:07:53Z",
    "status": "operational"
  },
  {
    "timestamp": "2026-05-23T04:12:55Z",
    "status": "operational"
  },
  {
    "timestamp": "2026-05-23T04:17:57Z",
    "status": "operational"
  },
  {
    "timestamp": "2026-05-23T04:22:58Z",
    "status": "operational"
  },
  {
    "timestamp": "2026-05-23T04:28:00Z",
    "status": "operational"
  },
  {
    "timestamp": "2026-05-23T04:33:01Z",
    "status": "operational"
  },
  {
    "timestamp": "2026-05-23T04:38:03Z",
    "status": "operational"
  },
  {
    "timestamp": "2026-05-23T04:43:05Z",
    "status": "operational"
  },
  {
    "timestamp": "2026-05-23T04:48:06Z",
    "status": "operational"
  },
  {
    "timestamp": "2026-05-23T04:53:08Z",
    "status": "operational"
  },
  {
    "timestamp": "2026-05-23T04:58:09Z",
    "status": "operational"
  },
  {
    "timestamp": "2026-05-23T05:03:11Z",
    "status": "operational"
  },
  {
    "timestamp": "2026-05-23T05:08:13Z",
    "status": "operational"
  },
  {
    "timestamp": "2026-05-23T05:13:14Z",
    "status": "operational"
  },
  {
    "timestamp": "2026-05-23T05:18:16Z",
    "status": "operational"
  },
  {
    "timestamp": "2026-05-23T05:23:17Z",
    "status": "operational"
  },
  {
    "timestamp": "2026-05-23T05:28:19Z",
    "status": "operational"
  },
  {
    "timestamp": "2026-05-23T05:33:20Z",
    "status": "operational"
  },
  {
    "timestamp": "2026-05-23T05:38:22Z",
    "status": "operational"
  },
  {
    "timestamp": "2026-05-23T05:43:24Z",
    "status": "operational"
  },
  {
    "timestamp": "2026-05-23T05:48:26Z",
    "status": "operational"
  },
  {
    "timestamp": "2026-05-23T05:53:27Z",
    "status": "operational"
  },
  {
    "timestamp": "2026-05-23T05:58:29Z",
    "status": "operational"
  },
  {
    "timestamp": "2026-05-23T06:03:30Z",
    "status": "operational"
  },
  {
    "timestamp": "2026-05-23T06:08:32Z",
    "status": "operational"
  },
  {
    "timestamp": "2026-05-23T06:13:34Z",
    "status": "operational"
  },
  {
    "timestamp": "2026-05-23T06:18:35Z",
    "status": "operational"
  },
  {
    "timestamp": "2026-05-23T06:23:37Z",
    "status": "operational"
  },
  {
    "timestamp": "2026-05-23T06:28:39Z",
    "status": "operational"
  },
  {
    "timestamp": "2026-05-23T06:33:40Z",
    "status": "operational"
  },
  {
    "timestamp": "2026-05-23T06:38:42Z",
    "status": "operational"
  },
  {
    "timestamp": "2026-05-23T06:43:43Z",
    "status": "operational"
  },
  {
    "timestamp": "2026-05-23T06:48:45Z",
    "status": "operational"
  },
  {
    "timestamp": "2026-05-23T06:53:46Z",
    "status": "operational"
  },
  {
    "timestamp": "2026-05-23T06:58:48Z",
    "status": "operational"
  },
  {
    "timestamp": "2026-05-23T07:03:50Z",
    "status": "operational"
  },
  {
    "timestamp": "2026-05-23T07:08:51Z",
    "status": "operational"
  },
  {
    "timestamp": "2026-05-23T07:13:53Z",
    "status": "operational"
  },
  {
    "timestamp": "2026-05-23T07:18:54Z",
    "status": "operational"
  },
  {
    "timestamp": "2026-05-23T07:23:56Z",
    "status": "operational"
  },
  {
    "timestamp": "2026-05-23T07:28:58Z",
    "status": "operational"
  },
  {
    "timestamp": "2026-05-23T07:33:59Z",
    "status": "operational"
  },
  {
    "timestamp": "2026-05-23T07:39:01Z",
    "status": "operational"
  },
  {
    "timestamp": "2026-05-23T07:44:02Z",
    "status": "operational"
  },
  {
    "timestamp": "2026-05-23T07:49:04Z",
    "status": "operational"
  },
  {
    "timestamp": "2026-05-23T07:54:06Z",
    "status": "operational"
  },
  {
    "timestamp": "2026-05-23T07:59:07Z",
    "status": "operational"
  },
  {
    "timestamp": "2026-05-23T08:04:09Z",
    "status": "operational"
  },
  {
    "timestamp": "2026-05-23T08:09:10Z",
    "status": "operational"
  },
  {
    "timestamp": "2026-05-23T08:14:12Z",
    "status": "operational"
  },
  {
    "timestamp": "2026-05-23T08:19:13Z",
    "status": "operational"
  },
  {
    "timestamp": "2026-05-23T08:24:15Z",
    "status": "operational"
  },
  {
    "timestamp": "2026-05-23T08:29:17Z",
    "status": "operational"
  },
  {
    "timestamp": "2026-05-23T08:34:18Z",
    "status": "operational"
  },
  {
    "timestamp": "2026-05-23T08:39:20Z",
    "status": "operational"
  },
  {
    "timestamp": "2026-05-23T08:44:22Z",
    "status": "operational"
  },
  {
    "timestamp": "2026-05-23T08:49:23Z",
    "status": "operational"
  },
  {
    "timestamp": "2026-05-23T08:54:25Z",
    "status": "operational"
  },
  {
    "timestamp": "2026-05-23T08:59:26Z",
    "status": "operational"
  },
  {
    "timestamp": "2026-05-23T09:04:28Z",
    "status": "operational"
  },
  {
    "timestamp": "2026-05-23T09:09:30Z",
    "status": "operational"
  },
  {
    "timestamp": "2026-05-23T09:14:31Z",
    "status": "operational"
  },
  {
    "timestamp": "2026-05-23T09:19:33Z",
    "status": "operational"
  },
  {
    "timestamp": "2026-05-23T09:24:34Z",
    "status": "operational"
  },
  {
    "timestamp": "2026-05-23T09:29:36Z",
    "status": "operational"
  },
  {
    "timestamp": "2026-05-23T09:34:37Z",
    "status": "operational"
  },
  {
    "timestamp": "2026-05-23T09:39:39Z",
    "status": "operational"
  },
  {
    "timestamp": "2026-05-23T09:44:41Z",
    "status": "operational"
  },
  {
    "timestamp": "2026-05-23T09:49:43Z",
    "status": "operational"
  },
  {
    "timestamp": "2026-05-23T09:54:44Z",
    "status": "operational"
  },
  {
    "timestamp": "2026-05-23T09:59:46Z",
    "status": "operational"
  },
  {
    "timestamp": "2026-05-23T10:04:47Z",
    "status": "operational"
  },
  {
    "timestamp": "2026-05-23T10:09:49Z",
    "status": "operational"
  },
  {
    "timestamp": "2026-05-23T10:14:50Z",
    "status": "operational"
  },
  {
    "timestamp": "2026-05-23T10:19:52Z",
    "status": "operational"
  },
  {
    "timestamp": "2026-05-23T10:24:53Z",
    "status": "operational"
  },
  {
    "timestamp": "2026-05-23T10:29:55Z",
    "status": "operational"
  },
  {
    "timestamp": "2026-05-23T10:34:57Z",
    "status": "operational"
  },
  {
    "timestamp": "2026-05-23T10:39:58Z",
    "status": "operational"
  },
  {
    "timestamp": "2026-05-23T10:45:00Z",
    "status": "operational"
  },
  {
    "timestamp": "2026-05-23T10:50:02Z",
    "status": "operational"
  },
  {
    "timestamp": "2026-05-23T10:55:03Z",
    "status": "operational"
  },
  {
    "timestamp": "2026-05-23T11:00:05Z",
    "status": "operational"
  },
  {
    "timestamp": "2026-05-23T11:05:07Z",
    "status": "operational"
  },
  {
    "timestamp": "2026-05-23T11:10:08Z",
    "status": "operational"
  },
  {
    "timestamp": "2026-05-23T11:15:10Z",
    "status": "operational"
  },
  {
    "timestamp": "2026-05-23T11:20:11Z",
    "status": "operational"
  },
  {
    "timestamp": "2026-05-23T11:25:13Z",
    "status": "operational"
  },
  {
    "timestamp": "2026-05-23T11:30:14Z",
    "status": "operational"
  },
  {
    "timestamp": "2026-05-23T11:35:16Z",
    "status": "operational"
  },
  {
    "timestamp": "2026-05-23T11:40:18Z",
    "status": "operational"
  },
  {
    "timestamp": "2026-05-23T11:45:19Z",
    "status": "operational"
  },
  {
    "timestamp": "2026-05-23T11:46:14Z",
    "status": "operational"
  },
  {
    "timestamp": "2026-05-23T11:46:22Z",
    "status": "operational"
  },
  {
    "timestamp": "2026-05-23T11:51:24Z",
    "status": "operational"
  },
  {
    "timestamp": "2026-05-23T11:56:26Z",
    "status": "operational"
  },
  {
    "timestamp": "2026-05-23T12:01:28Z",
    "status": "operational"
  },
  {
    "timestamp": "2026-05-23T12:06:31Z",
    "status": "operational"
  },
  {
    "timestamp": "2026-05-23T12:11:33Z",
    "status": "operational"
  },
  {
    "timestamp": "2026-05-23T12:16:35Z",
    "status": "operational"
  },
  {
    "timestamp": "2026-05-23T12:21:37Z",
    "status": "operational"
  },
  {
    "timestamp": "2026-05-23T12:26:39Z",
    "status": "operational"
  },
  {
    "timestamp": "2026-05-23T12:31:41Z",
    "status": "operational"
  },
  {
    "timestamp": "2026-05-23T12:36:43Z",
    "status": "operational"
  },
  {
    "timestamp": "2026-05-23T12:41:45Z",
    "status": "operational"
  },
  {
    "timestamp": "2026-05-23T12:46:47Z",
    "status": "operational"
  },
  {
    "timestamp": "2026-05-23T12:51:49Z",
    "status": "operational"
  },
  {
    "timestamp": "2026-05-23T12:56:51Z",
    "status": "operational"
  },
  {
    "timestamp": "2026-05-23T13:01:53Z",
    "status": "operational"
  },
  {
    "timestamp": "2026-05-23T13:06:56Z",
    "status": "operational"
  },
  {
    "timestamp": "2026-05-23T13:11:58Z",
    "status": "operational"
  },
  {
    "timestamp": "2026-05-23T13:17:00Z",
    "status": "operational"
  },
  {
    "timestamp": "2026-05-23T13:22:02Z",
    "status": "operational"
  },
  {
    "timestamp": "2026-05-23T13:27:04Z",
    "status": "operational"
  },
  {
    "timestamp": "2026-05-23T13:32:06Z",
    "status": "operational"
  },
  {
    "timestamp": "2026-05-23T13:37:08Z",
    "status": "operational"
  },
  {
    "timestamp": "2026-05-23T13:42:10Z",
    "status": "operational"
  },
  {
    "timestamp": "2026-05-23T13:47:12Z",
    "status": "operational"
  },
  {
    "timestamp": "2026-05-23T13:52:14Z",
    "status": "operational"
  },
  {
    "timestamp": "2026-05-23T13:57:16Z",
    "status": "operational"
  },
  {
    "timestamp": "2026-05-23T14:02:18Z",
    "status": "operational"
  },
  {
    "timestamp": "2026-05-23T14:07:21Z",
    "status": "operational"
  },
  {
    "timestamp": "2026-05-23T14:12:23Z",
    "status": "operational"
  },
  {
    "timestamp": "2026-05-23T14:17:25Z",
    "status": "operational"
  },
  {
    "timestamp": "2026-05-23T14:22:27Z",
    "status": "operational"
  },
  {
    "timestamp": "2026-05-23T14:27:29Z",
    "status": "operational"
  },
  {
    "timestamp": "2026-05-23T14:32:32Z",
    "status": "operational"
  },
  {
    "timestamp": "2026-05-23T14:37:34Z",
    "status": "operational"
  },
  {
    "timestamp": "2026-05-23T14:42:36Z",
    "status": "operational"
  },
  {
    "timestamp": "2026-05-23T14:47:39Z",
    "status": "operational"
  },
  {
    "timestamp": "2026-05-23T14:52:41Z",
    "status": "operational"
  },
  {
    "timestamp": "2026-05-23T14:57:43Z",
    "status": "operational"
  },
  {
    "timestamp": "2026-05-23T15:02:45Z",
    "status": "operational"
  },
  {
    "timestamp": "2026-05-23T15:07:47Z",
    "status": "operational"
  },
  {
    "timestamp": "2026-05-23T15:12:49Z",
    "status": "operational"
  },
  {
    "timestamp": "2026-05-23T15:17:51Z",
    "status": "operational"
  },
  {
    "timestamp": "2026-05-23T15:22:53Z",
    "status": "operational"
  },
  {
    "timestamp": "2026-05-23T15:27:56Z",
    "status": "operational"
  },
  {
    "timestamp": "2026-05-23T15:32:58Z",
    "status": "operational"
  },
  {
    "timestamp": "2026-05-23T15:38:01Z",
    "status": "operational"
  },
  {
    "timestamp": "2026-05-23T15:43:03Z",
    "status": "operational"
  },
  {
    "timestamp": "2026-05-23T15:48:05Z",
    "status": "operational"
  },
  {
    "timestamp": "2026-05-23T15:53:07Z",
    "status": "operational"
  },
  {
    "timestamp": "2026-05-23T15:58:09Z",
    "status": "operational"
  },
  {
    "timestamp": "2026-05-23T16:03:11Z",
    "status": "operational"
  },
  {
    "timestamp": "2026-05-23T16:08:13Z",
    "status": "operational"
  },
  {
    "timestamp": "2026-05-23T16:13:15Z",
    "status": "operational"
  },
  {
    "timestamp": "2026-05-23T16:18:17Z",
    "status": "operational"
  },
  {
    "timestamp": "2026-05-23T16:23:19Z",
    "status": "operational"
  },
  {
    "timestamp": "2026-05-23T16:28:21Z",
    "status": "operational"
  },
  {
    "timestamp": "2026-05-23T16:33:23Z",
    "status": "operational"
  },
  {
    "timestamp": "2026-05-23T16:38:25Z",
    "status": "operational"
  },
  {
    "timestamp": "2026-05-23T16:43:27Z",
    "status": "operational"
  },
  {
    "timestamp": "2026-05-23T16:48:29Z",
    "status": "operational"
  },
  {
    "timestamp": "2026-05-23T16:53:31Z",
    "status": "operational"
  },
  {
    "timestamp": "2026-05-23T16:58:33Z",
    "status": "operational"
  },
  {
    "timestamp": "2026-05-23T17:03:36Z",
    "status": "operational"
  },
  {
    "timestamp": "2026-05-23T17:08:38Z",
    "status": "operational"
  },
  {
    "timestamp": "2026-05-23T17:13:40Z",
    "status": "operational"
  },
  {
    "timestamp": "2026-05-23T17:18:42Z",
    "status": "operational"
  },
  {
    "timestamp": "2026-05-23T17:23:44Z",
    "status": "operational"
  },
  {
    "timestamp": "2026-05-23T17:28:46Z",
    "status": "operational"
  },
  {
    "timestamp": "2026-05-23T17:33:48Z",
    "status": "operational"
  },
  {
    "timestamp": "2026-05-23T17:38:50Z",
    "status": "operational"
  },
  {
    "timestamp": "2026-05-23T17:43:52Z",
    "status": "operational"
  },
  {
    "timestamp": "2026-05-23T17:48:54Z",
    "status": "operational"
  },
  {
    "timestamp": "2026-05-23T17:53:56Z",
    "status": "operational"
  },
  {
    "timestamp": "2026-05-23T17:58:58Z",
    "status": "operational"
  },
  {
    "timestamp": "2026-05-23T18:04:00Z",
    "status": "operational"
  },
  {
    "timestamp": "2026-05-23T18:09:02Z",
    "status": "operational"
  },
  {
    "timestamp": "2026-05-23T18:14:04Z",
    "status": "operational"
  },
  {
    "timestamp": "2026-05-23T18:19:06Z",
    "status": "operational"
  },
  {
    "timestamp": "2026-05-23T18:24:08Z",
    "status": "operational"
  },
  {
    "timestamp": "2026-05-23T18:29:10Z",
    "status": "operational"
  },
  {
    "timestamp": "2026-05-23T18:34:12Z",
    "status": "operational"
  },
  {
    "timestamp": "2026-05-23T18:39:14Z",
    "status": "operational"
  },
  {
    "timestamp": "2026-05-23T18:44:16Z",
    "status": "operational"
  },
  {
    "timestamp": "2026-05-23T18:49:18Z",
    "status": "operational"
  },
  {
    "timestamp": "2026-05-23T18:54:20Z",
    "status": "operational"
  },
  {
    "timestamp": "2026-05-23T18:59:22Z",
    "status": "operational"
  },
  {
    "timestamp": "2026-05-23T19:04:24Z",
    "status": "operational"
  },
  {
    "timestamp": "2026-05-23T19:09:26Z",
    "status": "operational"
  },
  {
    "timestamp": "2026-05-23T19:14:28Z",
    "status": "operational"
  },
  {
    "timestamp": "2026-05-23T19:19:30Z",
    "status": "operational"
  },
  {
    "timestamp": "2026-05-23T19:24:32Z",
    "status": "operational"
  },
  {
    "timestamp": "2026-05-23T19:29:34Z",
    "status": "operational"
  },
  {
    "timestamp": "2026-05-23T19:34:36Z",
    "status": "operational"
  },
  {
    "timestamp": "2026-05-23T19:39:38Z",
    "status": "operational"
  },
  {
    "timestamp": "2026-05-23T19:44:40Z",
    "status": "operational"
  },
  {
    "timestamp": "2026-05-23T19:49:42Z",
    "status": "operational"
  },
  {
    "timestamp": "2026-05-23T19:54:44Z",
    "status": "operational"
  },
  {
    "timestamp": "2026-05-23T19:59:46Z",
    "status": "operational"
  },
  {
    "timestamp": "2026-05-23T20:04:48Z",
    "status": "operational"
  },
  {
    "timestamp": "2026-05-23T20:09:51Z",
    "status": "operational"
  },
  {
    "timestamp": "2026-05-23T20:14:53Z",
    "status": "operational"
  },
  {
    "timestamp": "2026-05-23T20:19:55Z",
    "status": "operational"
  },
  {
    "timestamp": "2026-05-23T20:24:56Z",
    "status": "operational"
  },
  {
    "timestamp": "2026-05-23T20:29:59Z",
    "status": "operational"
  },
  {
    "timestamp": "2026-05-23T20:35:01Z",
    "status": "operational"
  },
  {
    "timestamp": "2026-05-23T20:40:03Z",
    "status": "operational"
  },
  {
    "timestamp": "2026-05-23T20:45:05Z",
    "status": "operational"
  },
  {
    "timestamp": "2026-05-23T20:50:07Z",
    "status": "operational"
  },
  {
    "timestamp": "2026-05-23T20:55:09Z",
    "status": "operational"
  },
  {
    "timestamp": "2026-05-23T21:00:11Z",
    "status": "operational"
  },
  {
    "timestamp": "2026-05-23T21:05:13Z",
    "status": "operational"
  }
]
